Workbook

Sheet Sheet1
A1: task_id | B1: statement | C1: code | D1: answer | E1: url | F1: input | G1: source | H1: data_id | I1: location | J1: last_error_details | K1: evaluated | L1: evaluated_array | M1: actual_verdict | N1: llm_verdict | O1: llm_answer | P1: llm_reason | Q1: final verdict
A2: 1 | B2: Anton has the integer x. He is interested what positive integer, which doesn't exceed x, has the maximum sum of digits. Your task is to help Anton and to find the integer that interests him. If there are several such integers, determine the biggest of them. -----Input----- The first line contains the positive integer x (1 ≤ x ≤ 10^18) — the integer which Anton has. -----Output----- Print the positive integer which doesn't exceed x and has the maximum sum of digits. If there are several such integers, print the biggest of them. Printed integer must not contain leading zeros. -----Examples----- Input 100 Output 99 Input 48 Output 48 Input 521 Output 499 | C2: def max_sum_digits(n): n = str(n) if len(n) == 1: return int(n) if '9' * len(n) <= n: return int('9' * len(n)) for i in range(len(n)): if n[i] != '9': return int(n[:i] + str(int(n[i]) - 1) + '9' * (len(n) - i - 1)) n = int(input().strip()) print(max_sum_digits(n)) | D2: C | E2: https://codeforces.com/problemset/problem/770/B | F2: ## Problem ### Problem Description Anton has the integer x. He is interested what positive integer, which doesn't exceed x, has the maximum sum of digits. Your task is to help Anton and to find the integer that interests him. If there are several such integers, determine the biggest of them. -----Input----- The first line contains the positive integer x (1 ≤ x ≤ 10^18) — the integer which Anton has. -----Output----- Print the positive integer which doesn't exceed x and has the maximum sum of digits. If there are several such integers, print the biggest of them. Printed integer must not contain leading zeros. -----Examples----- Input 100 Output 99 Input 48 Output 48 Input 521 Output 499 ### Solution code file content to be Judged def max_sum_digits(n): n = str(n) if len(n) == 1: return int(n) if '9' * len(n) <= n: return int('9' * len(n)) for i in range(len(n)): if n[i] != '9': return int(n[:i] + str(int(n[i]) - 1) + '9' * (len(n) - i - 1)) n = int(input().strip()) print(max_sum_digits(n)) | G2: gpt4 | H2: 9 | I2: APPS/test/0001 | J2: {'input': '9590999\n', 'expected': '8999999\n', 'actual': '9499999\n'} | K2: C | L2: 201 AC, 69 WA, 0 CE, 8 RE, 0 TLE | M2: RE | N2: AC | O2: A | P2: STEP 1: The problem requires finding the largest integer less than or equal to a given integer x that has the maximum sum of its digits. If there are multiple integers with the same maximum digit sum, the largest integer should be chosen. The input constraint is that x is a positive integer up to 10^18. STEP 2: The code defines a function `max_sum_digits(n)` which takes an integer n as input. It first converts n to a string. If n is a single-digit number, it returns n itself since it is the only number with the maximum digit sum. If the number composed entirely of 9s with the same length as n is less than or equal to n, it returns that number. Otherwise, it iterates over the digits of n, and for the first non-9 digit, it decrements that digit by 1 and replaces all subsequent digits with 9s, then returns this new number. STEP 3: The code is correct for the problem requirements. It correctly identifies the largest number with the maximum digit sum by either using a number composed entirely of 9s or by decrementing the first non-9 digit and filling the rest with 9s. STEP 4: Not applicable as the code is correct. STEP 5: Not applicable as the code is correct. The code correctly implements the logic to find the largest integer with the maximum sum of digits that does not exceed the given integer x. | Q2: =_xlfn.XLOOKUP(H2,'final verdict'!F:F,'final verdict'!AJ:AJ,"") -> Misjudged wrong answer as correct: wrong answer on many cases but correct on a majority (reason: judge predicted a wrong expected output)
A3: 2 | B3: Apart from having lots of holidays throughout the year, residents of Berland also have whole lucky years. Year is considered lucky if it has no more than 1 non-zero digit in its number. So years 100, 40000, 5 are lucky and 12, 3001 and 12345 are not. You are given current year in Berland. Your task is to find how long will residents of Berland wait till the next lucky year. -----Input----- The first line contains integer number n (1 ≤ n ≤ 10^9) — current year in Berland. -----Output----- Output amount of years from the current year to the next lucky one. -----Examples----- Input 4 Output 1 Input 201 Output 99 Input 4000 Output 1000 -----Note----- In the first example next lucky year is 5. In the second one — 300. In the third — 5000. | C3: n = int(input()) if n % 10 == 0: print(1) elif n % 100 == 0: print(10) elif n % 1000 == 0: print(100) elif n % 10000 == 0: print(1000) else: print(10000) | D3: B | E3: https://codeforces.com/problemset/problem/808/A | F3: ## Problem ### Problem Description Apart from having lots of holidays throughout the year, residents of Berland also have whole lucky years. Year is considered lucky if it has no more than 1 non-zero digit in its number. So years 100, 40000, 5 are lucky and 12, 3001 and 12345 are not. You are given current year in Berland. Your task is to find how long will residents of Berland wait till the next lucky year. -----Input----- The first line contains integer number n (1 ≤ n ≤ 10^9) — current year in Berland. -----Output----- Output amount of years from the current year to the next lucky one. -----Examples----- Input 4 Output 1 Input 201 Output 99 Input 4000 Output 1000 -----Note----- In the first example next lucky year is 5. In the second one — 300. In the third — 5000. ### Solution code file content to be Judged n = int(input()) if n % 10 == 0: print(1) elif n % 100 == 0: print(10) elif n % 1000 == 0: print(100) elif n % 10000 == 0: print(1000) else: print(10000) | G3: gemma | H3: 15 | I3: APPS/test/0002 | J3: {'input': '90900\n', 'expected': '9100\n', 'actual': ''} | K3: B | L3: 0 AC, 0 WA, 271 CE, 0 RE, 0 TLE | M3: CE | N3: WA | O3: C | P3: STEP 1: The problem requires finding the next 'lucky year' after a given year 'n'. A lucky year is defined as a year with no more than one non-zero digit. The task is to calculate how many years it will take to reach the next lucky year from the given year 'n'. STEP 2: Analyzing the code: - `n = int(input())`: Reads the input year and converts it to an integer. - `if n % 10 == 0:`: Checks if the year is a multiple of 10. If true, it prints 1, assuming the next lucky year is 1 year away. - `elif n % 100 == 0:`: Checks if the year is a multiple of 100. If true, it prints 10, assuming the next lucky year is 10 years away. - `elif n % 1000 == 0:`: Checks if the year is a multiple of 1000. If true, it prints 100, assuming the next lucky year is 100 years away. - `elif n % 10000 == 0:`: Checks if the year is a multiple of 10000. If true, it prints 1000, assuming the next lucky year is 1000 years away. - `else:`: If none of the above conditions are met, it prints 10000, assuming the next lucky year is 10000 years away. STEP 3: The code is incorrect. It does not correctly calculate the next lucky year based on the definition provided. The logic only checks for multiples of 10, 100, 1000, and 10000, which does not align with the requirement of having no more than one non-zero digit. STEP 4: A specific test case where the code fails is `n = 201`. The correct output should be 99, as the next lucky year is 300. However, the code will output 10000, which is incorrect. STEP 5: The root cause of the failure is that the code does not correctly identify the next lucky year based on the number of non-zero digits. It only checks for specific multiples, which does not cover all possible cases of lucky years. Verdict: WA (Wrong Answer) Answer: C | Q3: =_xlfn.XLOOKUP(H3,'final verdict'!F:F,'final verdict'!AJ:AJ,"") -> Misjudged compilation error as wrong answer: indentation issue
A4: 6 | B4: You are fighting with Zmei Gorynich — a ferocious monster from Slavic myths, a huge dragon-like reptile with multiple heads! $m$ Initially Zmei Gorynich has $x$ heads. You can deal $n$ types of blows. If you deal a blow of the $i$-th type, you decrease the number of Gorynich's heads by $min(d_i, curX)$, there $curX$ is the current number of heads. But if after this blow Zmei Gorynich has at least one head, he grows $h_i$ new heads. If $curX = 0$ then Gorynich is defeated. You can deal each blow any number of times, in any order. For example, if $curX = 10$, $d = 7$, $h = 10$ then the number of heads changes to $13$ (you cut $7$ heads off, but then Zmei grows $10$ new ones), but if $curX = 10$, $d = 11$, $h = 100$ then number of heads changes to $0$ and Zmei Gorynich is considered defeated. Calculate the minimum number of blows to defeat Zmei Gorynich! You have to answer $t$ independent queries. -----Input----- The first line contains one integer $t$ ($1 \le t \le 100$) – the number of queries. The first line of each query contains two integers $n$ and $x$ ($1 \le n \le 100$, $1 \le x \le 10^9$) — the number of possible types of blows and the number of heads Zmei initially has, respectively. The following $n$ lines of each query contain the descriptions of types of blows you can deal. The $i$-th line contains two integers $d_i$ and $h_i$ ($1 \le d_i, h_i \le 10^9$) — the description of the $i$-th blow. -----Output----- For each query print the minimum number of blows you have to deal to defeat Zmei Gorynich. If Zmei Gorynuch cannot be defeated print $-1$. -----Example----- Input 3 3 10 6 3 8 2 1 4 4 10 4 1 3 2 2 6 1 100 2 15 10 11 14 100 Output 2 3 -1 -----Note----- In the first query you can deal the first blow (after that the number of heads changes to $10 - 6 + 3 = 7$), and then deal the second blow. In the second query you just deal the first blow three times, and Zmei is defeated. In third query you can not defeat Zmei Gorynich. Maybe it's better to convince it to stop fighting? | C4: t = int(input()) for _ in range(t): n, x = map(int, input().split()) max_d = max_h = 0 for _ in range(n): d, h = map(int, input().split()) max_d = max(max_d, d) max_h = max(max_h, d - h) if x <= max_d: print(1) elif max_h <= 0: print(-1) else: print((x - max_d + max_h - 1) // max_h + 1) | D4: A | E4: https://codeforces.com/problemset/problem/1217/B | F4: ## Problem ### Problem Description You are fighting with Zmei Gorynich — a ferocious monster from Slavic myths, a huge dragon-like reptile with multiple heads! $m$ Initially Zmei Gorynich has $x$ heads. You can deal $n$ types of blows. If you deal a blow of the $i$-th type, you decrease the number of Gorynich's heads by $min(d_i, curX)$, there $curX$ is the current number of heads. But if after this blow Zmei Gorynich has at least one head, he grows $h_i$ new heads. If $curX = 0$ then Gorynich is defeated. You can deal each blow any number of times, in any order. For example, if $curX = 10$, $d = 7$, $h = 10$ then the number of heads changes to $13$ (you cut $7$ heads off, but then Zmei grows $10$ new ones), but if $curX = 10$, $d = 11$, $h = 100$ then number of heads changes to $0$ and Zmei Gorynich is considered defeated. Calculate the minimum number of blows to defeat Zmei Gorynich! You have to answer $t$ independent queries. -----Input----- The first line contains one integer $t$ ($1 \le t \le 100$) – the number of queries. The first line of each query contains two integers $n$ and $x$ ($1 \le n \le 100$, $1 \le x \le 10^9$) — the number of possible types of blows and the number of heads Zmei initially has, respectively. The following $n$ lines of each query contain the descriptions of types of blows you can deal. The $i$-th line contains two integers $d_i$ and $h_i$ ($1 \le d_i, h_i \le 10^9$) — the description of the $i$-th blow. -----Output----- For each query print the minimum number of blows you have to deal to defeat Zmei Gorynich. If Zmei Gorynuch cannot be defeated print $-1$. -----Example----- Input 3 3 10 6 3 8 2 1 4 4 10 4 1 3 2 2 6 1 100 2 15 10 11 14 100 Output 2 3 -1 -----Note----- In the first query you can deal the first blow (after that the number of heads changes to $10 - 6 + 3 = 7$), and then deal the second blow. In the second query you just deal the first blow three times, and Zmei is defeated. In third query you can not defeat Zmei Gorynich. Maybe it's better to convince it to stop fighting? ### Solution code file content to be Judged t = int(input()) for _ in range(t): n, x = map(int, input().split()) max_d = max_h = 0 for _ in range(n): d, h = map(int, input().split()) max_d = max(max_d, d) max_h = max(max_h, d - h) if x <= max_d: print(1) elif max_h <= 0: print(-1) else: print((x - max_d + max_h - 1) // max_h + 1) | G4: gpt4 | H4: 32 | I4: APPS/test/0006 | K4: A | L4: 224 AC, 0 WA, 0 CE, 0 RE, 0 TLE | M4: AC | N4: WA | O4: C | P4: STEP 1: The problem requires determining the minimum number of blows needed to defeat Zmei Gorynich, a monster with multiple heads. Each blow type reduces the number of heads by a certain amount and may cause the monster to grow new heads. The goal is to find the minimum number of blows to reduce the monster's heads to zero, or determine if it's impossible. STEP 2: The code begins by reading the number of test cases `t`. For each test case, it reads the number of blow types `n` and the initial number of heads `x`. It initializes `max_d` to track the maximum damage a single blow can do and `max_h` to track the maximum net damage (damage minus regrowth) a blow can achieve. It then iterates over each blow type, updating `max_d` and `max_h` accordingly. After processing all blow types, it checks if the monster can be defeated in one blow (`x <= max_d`). If not, it checks if any blow results in a net reduction of heads (`max_h > 0`). If no net reduction is possible, it prints `-1`. Otherwise, it calculates the minimum number of blows needed using the formula `(x - max_d + max_h - 1) // max_h + 1` and prints the result. STEP 3: The code is incorrect. It fails to correctly calculate the minimum number of blows in some cases. STEP 4: Consider the input: 1 2 15 10 11 14 100 The expected output is `-1` because no blow can reduce the heads to zero, but the code outputs `-1`, which is correct. However, the logic for calculating the number of blows is flawed in other cases. STEP 5: The root cause of the failure is the incorrect calculation of the number of blows needed. The formula `(x - max_d + max_h - 1) // max_h + 1` does not correctly account for the sequence of blows needed to reduce the heads to zero. The code assumes that the maximum damage blow is always used first, which may not be optimal. Additionally, the calculation of `max_h` as `d - h` is incorrect because it should consider the net effect of repeatedly using a blow type, not just the difference for a single blow. | Q4: =_xlfn.XLOOKUP(H4,'final verdict'!F:F,'final verdict'!AJ:AJ,"") -> Misjudged correct as wrong answer: rationale is incorrect (reason: judge predicted a wrong expected output)
A5: 11 | B5: Little Joty has got a task to do. She has a line of n tiles indexed from 1 to n. She has to paint them in a strange pattern. An unpainted tile should be painted Red if it's index is divisible by a and an unpainted tile should be painted Blue if it's index is divisible by b. So the tile with the number divisible by a and b can be either painted Red or Blue. After her painting is done, she will get p chocolates for each tile that is painted Red and q chocolates for each tile that is painted Blue. Note that she can paint tiles in any order she wants. Given the required information, find the maximum number of chocolates Joty can get. -----Input----- The only line contains five integers n, a, b, p and q (1 ≤ n, a, b, p, q ≤ 10^9). -----Output----- Print the only integer s — the maximum number of chocolates Joty can get. Note that the answer can be too large, so you should use 64-bit integer type to store it. In C++ you can use the long long integer type and in Java you can use long integer type. -----Examples----- Input 5 2 3 12 15 Output 39 Input 20 2 3 3 5 Output 51 | C5: def max_chocolates(): n, a, b, p, q = map(int, input().split()) lcm = a * b // math.gcd(a, b) red_tiles = n // a blue_tiles = n // b common_tiles = n // lcm red_chocolates = red_tiles * p blue_chocolates = blue_tiles * q common_chocolates = common_tiles * min(p, q) total_chocolates = red_chocolates + blue_chocolates - common_chocolates return total_chocolates import math print(max_chocolates()) | D5: A | E5: https://codeforces.com/problemset/problem/678/C | F5: ## Problem ### Problem Description Little Joty has got a task to do. She has a line of n tiles indexed from 1 to n. She has to paint them in a strange pattern. An unpainted tile should be painted Red if it's index is divisible by a and an unpainted tile should be painted Blue if it's index is divisible by b. So the tile with the number divisible by a and b can be either painted Red or Blue. After her painting is done, she will get p chocolates for each tile that is painted Red and q chocolates for each tile that is painted Blue. Note that she can paint tiles in any order she wants. Given the required information, find the maximum number of chocolates Joty can get. -----Input----- The only line contains five integers n, a, b, p and q (1 ≤ n, a, b, p, q ≤ 10^9). -----Output----- Print the only integer s — the maximum number of chocolates Joty can get. Note that the answer can be too large, so you should use 64-bit integer type to store it. In C++ you can use the long long integer type and in Java you can use long integer type. -----Examples----- Input 5 2 3 12 15 Output 39 Input 20 2 3 3 5 Output 51 ### Solution code file content to be Judged def max_chocolates(): n, a, b, p, q = map(int, input().split()) lcm = a * b // math.gcd(a, b) red_tiles = n // a blue_tiles = n // b common_tiles = n // lcm red_chocolates = red_tiles * p blue_chocolates = blue_tiles * q common_chocolates = common_tiles * min(p, q) total_chocolates = red_chocolates + blue_chocolates - common_chocolates return total_chocolates import math print(max_chocolates()) | G5: deepseekcoder | H5: 52 | I5: APPS/test/0011 | K5: A | L5: 185 AC, 0 WA, 0 CE, 0 RE, 0 TLE | M5: AC | N5: WA | O5: C | P5: STEP 1: The problem requires calculating the maximum number of chocolates Joty can get by painting tiles. Tiles are painted Red if their index is divisible by 'a' and Blue if divisible by 'b'. If a tile's index is divisible by both 'a' and 'b', it can be painted either Red or Blue. Joty receives 'p' chocolates for each Red tile and 'q' chocolates for each Blue tile. The goal is to maximize the chocolates received. STEP 2: The code begins by reading input values for n, a, b, p, and q. It calculates the least common multiple (LCM) of 'a' and 'b' using the formula `lcm = a * b // math.gcd(a, b)`. This LCM is used to determine the number of tiles that are divisible by both 'a' and 'b'. The code calculates: - `red_tiles` as the number of tiles divisible by 'a'. - `blue_tiles` as the number of tiles divisible by 'b'. - `common_tiles` as the number of tiles divisible by both 'a' and 'b'. It then calculates the chocolates: - `red_chocolates` as the chocolates from Red tiles. - `blue_chocolates` as the chocolates from Blue tiles. - `common_chocolates` as the chocolates from common tiles, using the minimum of 'p' and 'q' to avoid double counting. Finally, it calculates `total_chocolates` by adding `red_chocolates` and `blue_chocolates` and subtracting `common_chocolates` to avoid double counting the common tiles. STEP 3: The code is incorrect. It does not correctly maximize the chocolates because it subtracts `common_chocolates` using `min(p, q)`, which does not account for maximizing the chocolates from common tiles. STEP 4: A test case that causes the code to fail is: Input: 6 2 3 10 5 Expected Output: 30 STEP 5: The root cause of the failure is that the code subtracts `common_chocolates` using `min(p, q)`, which does not maximize the chocolates. Instead, for common tiles, it should choose the maximum of 'p' or 'q' to maximize the chocolates received. The correct approach should be: - Calculate `red_chocolates` as `(red_tiles - common_tiles) * p`. - Calculate `blue_chocolates` as `(blue_tiles - common_tiles) * q`. - Calculate `common_chocolates` as `common_tiles * max(p, q)`. - Then, `total_chocolates = red_chocolates + blue_chocolates + common_chocolates`. | Q5: =_xlfn.XLOOKUP(H5,'final verdict'!F:F,'final verdict'!AJ:AJ,"") -> Misjudged correct as wrong answer: rationale is incorrect (reason: judge predicted a wrong expected output)
A6: 11 | B6: Little Joty has got a task to do. She has a line of n tiles indexed from 1 to n. She has to paint them in a strange pattern. An unpainted tile should be painted Red if it's index is divisible by a and an unpainted tile should be painted Blue if it's index is divisible by b. So the tile with the number divisible by a and b can be either painted Red or Blue. After her painting is done, she will get p chocolates for each tile that is painted Red and q chocolates for each tile that is painted Blue. Note that she can paint tiles in any order she wants. Given the required information, find the maximum number of chocolates Joty can get. -----Input----- The only line contains five integers n, a, b, p and q (1 ≤ n, a, b, p, q ≤ 10^9). -----Output----- Print the only integer s — the maximum number of chocolates Joty can get. Note that the answer can be too large, so you should use 64-bit integer type to store it. In C++ you can use the long long integer type and in Java you can use long integer type. -----Examples----- Input 5 2 3 12 15 Output 39 Input 20 2 3 3 5 Output 51 | C6: n, a, b, p, q = map(int, input().split()) s = 0 for i in range(1, n+1): if i % a == 0 and i % b == 0: s += p + q elif i % a == 0: s += p elif i % b == 0: s += q print(s) | D6: B | E6: https://codeforces.com/problemset/problem/678/C | F6: ## Problem ### Problem Description Little Joty has got a task to do. She has a line of n tiles indexed from 1 to n. She has to paint them in a strange pattern. An unpainted tile should be painted Red if it's index is divisible by a and an unpainted tile should be painted Blue if it's index is divisible by b. So the tile with the number divisible by a and b can be either painted Red or Blue. After her painting is done, she will get p chocolates for each tile that is painted Red and q chocolates for each tile that is painted Blue. Note that she can paint tiles in any order she wants. Given the required information, find the maximum number of chocolates Joty can get. -----Input----- The only line contains five integers n, a, b, p and q (1 ≤ n, a, b, p, q ≤ 10^9). -----Output----- Print the only integer s — the maximum number of chocolates Joty can get. Note that the answer can be too large, so you should use 64-bit integer type to store it. In C++ you can use the long long integer type and in Java you can use long integer type. -----Examples----- Input 5 2 3 12 15 Output 39 Input 20 2 3 3 5 Output 51 ### Solution code file content to be Judged n, a, b, p, q = map(int, input().split()) s = 0 for i in range(1, n+1): if i % a == 0 and i % b == 0: s += p + q elif i % a == 0: s += p elif i % b == 0: s += q print(s) | G6: gemma | H6: 57 | I6: APPS/test/0011 | J6: {'input': '100 8 12 5 6\n', 'expected': '88\n', 'actual': ''} | K6: B | L6: 0 AC, 0 WA, 185 CE, 0 RE, 0 TLE | M6: CE | N6: WA | O6: C | P6: STEP 1: The problem requires calculating the maximum number of chocolates Joty can get by painting tiles in a specific pattern. Tiles are painted Red if their index is divisible by 'a' and Blue if divisible by 'b'. If a tile's index is divisible by both 'a' and 'b', it can be painted either Red or Blue. The goal is to maximize the chocolates, where each Red tile gives 'p' chocolates and each Blue tile gives 'q' chocolates. STEP 2: Analyzing the code: - The code reads five integers: n, a, b, p, q. - It initializes a variable 's' to 0 to store the total chocolates. - It iterates over each tile index from 1 to n. - For each index, it checks: - If the index is divisible by both 'a' and 'b', it adds both 'p' and 'q' to 's'. - If the index is divisible only by 'a', it adds 'p' to 's'. - If the index is divisible only by 'b', it adds 'q' to 's'. - Finally, it prints the total chocolates 's'. STEP 3: The code is incorrect. It adds both 'p' and 'q' for indices divisible by both 'a' and 'b', which is not optimal. Instead, it should add the maximum of 'p' and 'q' for such indices to maximize chocolates. STEP 4: A test case that causes the code to fail: - Input: 6 2 3 10 20 - Expected Output: 70 (indices 2, 4, 6 should be Red, and 3 should be Blue) - Actual Output: 80 (incorrect because it adds both 'p' and 'q' for index 6) STEP 5: The root cause of the failure is the logic that adds both 'p' and 'q' for indices divisible by both 'a' and 'b'. The correct approach is to add the maximum of 'p' and 'q' for such indices to ensure the maximum number of chocolates. Verdict: WA Answer: C | Q6: =_xlfn.XLOOKUP(H6,'final verdict'!F:F,'final verdict'!AJ:AJ,"") -> Misjudged compilation error as wrong answer: indentation issue
A7: 25 | B7: You are given matrix with n rows and n columns filled with zeroes. You should put k ones in it in such a way that the resulting matrix is symmetrical with respect to the main diagonal (the diagonal that goes from the top left to the bottom right corner) and is lexicographically maximal. One matrix is lexicographically greater than the other if the first different number in the first different row from the top in the first matrix is greater than the corresponding number in the second one. If there exists no such matrix then output -1. -----Input----- The first line consists of two numbers n and k (1 ≤ n ≤ 100, 0 ≤ k ≤ 10^6). -----Output----- If the answer exists then output resulting matrix. Otherwise output -1. -----Examples----- Input 2 1 Output 1 0 0 0 Input 3 2 Output 1 0 0 0 1 0 0 0 0 Input 2 5 Output -1 | C7: n, k = map(int, input().split()) if k > n*(n-1)//2: print("-1") else: matrix = [[0]*n for _ in range(n)] count = 0 for i in range(n): for j in range(i+1): if count < k: matrix[i][j] = 1 count += 1 for i in range(n-1, -1, -1): for j in range(n-1, i, -1): if count < k: matrix[i][j] = 1 count += 1 for i in range(n): print(" ".join(map(str, matrix[i])) | D7: B | E7: https://codeforces.com/problemset/problem/803/A | F7: ## Problem ### Problem Description You are given matrix with n rows and n columns filled with zeroes. You should put k ones in it in such a way that the resulting matrix is symmetrical with respect to the main diagonal (the diagonal that goes from the top left to the bottom right corner) and is lexicographically maximal. One matrix is lexicographically greater than the other if the first different number in the first different row from the top in the first matrix is greater than the corresponding number in the second one. If there exists no such matrix then output -1. -----Input----- The first line consists of two numbers n and k (1 ≤ n ≤ 100, 0 ≤ k ≤ 10^6). -----Output----- If the answer exists then output resulting matrix. Otherwise output -1. -----Examples----- Input 2 1 Output 1 0 0 0 Input 3 2 Output 1 0 0 0 1 0 0 0 0 Input 2 5 Output -1 ### Solution code file content to be Judged n, k = map(int, input().split()) if k > n*(n-1)//2: print("-1") else: matrix = [[0]*n for _ in range(n)] count = 0 for i in range(n): for j in range(i+1): if count < k: matrix[i][j] = 1 count += 1 for i in range(n-1, -1, -1): for j in range(n-1, i, -1): if count < k: matrix[i][j] = 1 count += 1 for i in range(n): print(" ".join(map(str, matrix[i])) | G7: wizardcoder | H7: 115 | I7: APPS/test/0025 | J7: {'input': '100 10001\n', 'expected': '-1\n', 'actual': ''} | K7: B | L7: 0 AC, 0 WA, 156 CE, 0 RE, 0 TLE | M7: CE | N7: WA | O7: C | P7: STEP 1: The problem requires creating an n x n matrix with k ones such that the matrix is symmetrical with respect to the main diagonal and is lexicographically maximal. If it's not possible to place k ones, the output should be -1. The constraints are 1 ≤ n ≤ 100 and 0 ≤ k ≤ 10^6. STEP 2: Analyzing the code: - Line 1: Reads the input values n and k. - Line 3: Checks if k is greater than n*(n-1)//2. This condition is incorrect because it checks if k is greater than the number of off-diagonal elements, but it should check if k is greater than n*n (the total number of elements in the matrix) since we can place ones on the diagonal as well. - Line 4: If the above condition is true, it prints "-1". This is incorrect because the condition itself is wrong. - Line 6: Initializes an n x n matrix filled with zeroes. - Line 7: Initializes a counter `count` to track the number of ones placed. - Lines 8-12: Iterates over the matrix to place ones in the lower triangle including the diagonal. This loop is correct for placing ones in the lower triangle. - Lines 13-17: Iterates over the matrix to place ones in the upper triangle excluding the diagonal. This loop is incorrect because it doesn't ensure symmetry with respect to the main diagonal. - Lines 18-19: Prints the matrix row by row. STEP 3: The code is incorrect because it does not correctly check the condition for when it's impossible to place k ones, and it does not ensure the matrix is symmetrical with respect to the main diagonal. STEP 4: A test case that causes the code to fail is n = 2, k = 3. The code will output a matrix with 3 ones, which is impossible for a 2x2 matrix. STEP 5: The root cause of the failure is the incorrect condition for checking if k ones can be placed and the incorrect logic for ensuring the matrix is symmetrical with respect to the main diagonal. | Q7: =_xlfn.XLOOKUP(H7,'final verdict'!F:F,'final verdict'!AJ:AJ,"") -> Misjudged compilation error as wrong answer: bracket mismatch
A8: 28 | B8: The All-Berland National Olympiad in Informatics has just ended! Now Vladimir wants to upload the contest from the Olympiad as a gym to a popular Codehorses website. Unfortunately, the archive with Olympiad's data is a mess. For example, the files with tests are named arbitrary without any logic. Vladimir wants to rename the files with tests so that their names are distinct integers starting from 1 without any gaps, namely, "1", "2", ..., "n', where n is the total number of tests. Some of the files contain tests from statements (examples), while others contain regular tests. It is possible that there are no examples, and it is possible that all tests are examples. Vladimir wants to rename the files so that the examples are the first several tests, all all the next files contain regular tests only. The only operation Vladimir can perform is the "move" command. Vladimir wants to write a script file, each of the lines in which is "move file_1 file_2", that means that the file "file_1" is to be renamed to "file_2". If there is a file "file_2" at the moment of this line being run, then this file is to be rewritten. After the line "move file_1 file_2" the file "file_1" doesn't exist, but there is a file "file_2" with content equal to the content of "file_1" before the "move" command. Help Vladimir to write the script file with the minimum possible number of lines so that after this script is run: all examples are the first several tests having filenames "1", "2", ..., "e", where e is the total number of examples; all other files contain regular tests with filenames "e + 1", "e + 2", ..., "n", where n is the total number of all tests. -----Input----- The first line contains single integer n (1 ≤ n ≤ 10^5) — the number of files with tests. n lines follow, each describing a file with test. Each line has a form of "name_i type_i", where "name_i" is the filename, and "type_i" equals "1", if the i-th file contains an example test, and "0" if it contains a regular test. Filenames of each file are strings of digits and small English letters with length from 1 to 6 characters. The filenames are guaranteed to be distinct. -----Output----- In the first line print the minimum number of lines in Vladimir's script file. After that print the script file, each line should be "move file_1 file_2", where "file_1" is an existing at the moment of this line being run filename, and "file_2" — is a string of digits and small English letters with length from 1 to 6. -----Examples----- Input 5 01 0 2 1 2extra 0 3 1 99 0 Output 4 move 3 1 move 01 5 move 2extra 4 move 99 3 Input 2 1 0 2 1 Output 3 move 1 3 move 2 1 move 3 2 Input 5 1 0 11 1 111 0 1111 1 11111 0 Output 5 move 1 5 move 11 1 move 1111 2 move 111 4 move 11111 3 | C8: import sys # Read the number of files from standard input n = int(input()) # Initialize the minimum number of lines required for the script min_lines = n # Read the files and their types from standard input files = [] for _ in range(n): file_name = input() type_ = input() files.append((file_name, type_)) # Rename the examples to the first few numbers examples = [file_ for file_ in files if file_.0 == "1"] example_indices = [i for i, file_ in enumerate(files) if file_.0 == "1"] min_lines = min(min_lines, len(example_indices)) # Rename the remaining files remaining_files = [file_ for file_ in files if file_.0 != "1"] for i in range(len(remaining_files)): file_name = remaining_files[i] new_file_name = str(i + 1) print("move", file_name, new_file_name) min_lines = min(min_lines, 1) print(f"Minimum number of lines in the script: {min_lines}") | D8: B | E8: https://codeforces.com/problemset/problem/858/E | F8: ## Problem ### Problem Description The All-Berland National Olympiad in Informatics has just ended! Now Vladimir wants to upload the contest from the Olympiad as a gym to a popular Codehorses website. Unfortunately, the archive with Olympiad's data is a mess. For example, the files with tests are named arbitrary without any logic. Vladimir wants to rename the files with tests so that their names are distinct integers starting from 1 without any gaps, namely, "1", "2", ..., "n', where n is the total number of tests. Some of the files contain tests from statements (examples), while others contain regular tests. It is possible that there are no examples, and it is possible that all tests are examples. Vladimir wants to rename the files so that the examples are the first several tests, all all the next files contain regular tests only. The only operation Vladimir can perform is the "move" command. Vladimir wants to write a script file, each of the lines in which is "move file_1 file_2", that means that the file "file_1" is to be renamed to "file_2". If there is a file "file_2" at the moment of this line being run, then this file is to be rewritten. After the line "move file_1 file_2" the file "file_1" doesn't exist, but there is a file "file_2" with content equal to the content of "file_1" before the "move" command. Help Vladimir to write the script file with the minimum possible number of lines so that after this script is run: all examples are the first several tests having filenames "1", "2", ..., "e", where e is the total number of examples; all other files contain regular tests with filenames "e + 1", "e + 2", ..., "n", where n is the total number of all tests. -----Input----- The first line contains single integer n (1 ≤ n ≤ 10^5) — the number of files with tests. n lines follow, each describing a file with test. Each line has a form of "name_i type_i", where "name_i" is the filename, and "type_i" equals "1", if the i-th file contains an example test, and "0" if it contains a regular test. Filenames of each file are strings of digits and small English letters with length from 1 to 6 characters. The filenames are guaranteed to be distinct. -----Output----- In the first line print the minimum number of lines in Vladimir's script file. After that print the script file, each line should be "move file_1 file_2", where "file_1" is an existing at the moment of this line being run filename, and "file_2" — is a string of digits and small English letters with length from 1 to 6. -----Examples----- Input 5 01 0 2 1 2extra 0 3 1 99 0 Output 4 move 3 1 move 01 5 move 2extra 4 move 99 3 Input 2 1 0 2 1 Output 3 move 1 3 move 2 1 move 3 2 Input 5 1 0 11 1 111 0 1111 1 11111 0 Output 5 move 1 5 move 11 1 move 1111 2 move 111 4 move 11111 3 ### Solution code file content to be Judged import sys # Read the number of files from standard input n = int(input()) # Initialize the minimum number of lines required for the script min_lines = n # Read the files and their types from standard input files = [] for _ in range(n): file_name = input() type_ = input() files.append((file_name, type_)) # Rename the examples to the first few numbers examples = [file_ for file_ in files if file_.0 == "1"] example_indices = [i for i, file_ in enumerate(files) if file_.0 == "1"] min_lines = min(min_lines, len(example_indices)) # Rename the remaining files remaining_files = [file_ for file_ in files if file_.0 != "1"] for i in range(len(remaining_files)): file_name = remaining_files[i] new_file_name = str(i + 1) print("move", file_name, new_file_name) min_lines = min(min_lines, 1) print(f"Minimum number of lines in the script: {min_lines}") | G8: llama | H8: 127 | I8: APPS/test/0028 | J8: {'input': '2\n01 0\n02 1\n', 'expected': '2\nmove 02 1\nmove 01 2\n', 'actual': ''} | K8: B | L8: 0 AC, 0 WA, 146 CE, 0 RE, 0 TLE | M8: CE | N8: WA | O8: C | P8: STEP 1: The problem requires renaming files such that example files are named with consecutive integers starting from 1, followed by regular test files. The goal is to achieve this with the minimum number of 'move' operations. Each file is initially named arbitrarily, and the task is to rename them according to their type (example or regular test) while maintaining the order of examples first. STEP 2: Analyzing the code: - The code starts by reading the number of files `n` from input. - It initializes `min_lines` to `n`, which is intended to track the minimum number of move operations. - It reads the file names and types into a list `files`. - It attempts to separate example files from regular files using list comprehensions. - It calculates `example_indices` to track indices of example files. - It attempts to rename remaining files, but the logic is flawed. STEP 3: The code is incorrect. It does not correctly handle the input format, and the logic for renaming files is not implemented correctly. Specifically, the code attempts to access `file_.0` which is incorrect syntax for accessing tuple elements in Python. Additionally, the logic for renaming files is incomplete and does not follow the problem requirements. STEP 4: A test case that would cause the code to fail is: ``` 3 file1 1 file2 0 file3 1 ``` This input would cause the code to fail due to incorrect tuple access and incomplete logic. STEP 5: The root cause of the failure is the incorrect syntax for accessing tuple elements (`file_.0` instead of `file_[0]`), and the incomplete logic for renaming files according to the problem requirements. The code does not correctly separate and rename example and regular files, nor does it handle the input format correctly. Verdict: The code has logical and execution issues, leading to a Wrong Answer (WA). | Q8: =_xlfn.XLOOKUP(H8,'final verdict'!F:F,'final verdict'!AJ:AJ,"") -> Misjudged compilation error as wrong answer: illegal expression (reason: illegal variable name)
A9: 31 | B9: ZS the Coder has recently found an interesting concept called the Birthday Paradox. It states that given a random set of 23 people, there is around 50% chance that some two of them share the same birthday. ZS the Coder finds this very interesting, and decides to test this with the inhabitants of Udayland. In Udayland, there are 2^{n} days in a year. ZS the Coder wants to interview k people from Udayland, each of them has birthday in one of 2^{n} days (each day with equal probability). He is interested in the probability of at least two of them have the birthday at the same day. ZS the Coder knows that the answer can be written as an irreducible fraction $\frac{A}{B}$. He wants to find the values of A and B (he does not like to deal with floating point numbers). Can you help him? -----Input----- The first and only line of the input contains two integers n and k (1 ≤ n ≤ 10^18, 2 ≤ k ≤ 10^18), meaning that there are 2^{n} days in a year and that ZS the Coder wants to interview exactly k people. -----Output----- If the probability of at least two k people having the same birthday in 2^{n} days long year equals $\frac{A}{B}$ (A ≥ 0, B ≥ 1, $\operatorname{gcd}(A, B) = 1$), print the A and B in a single line. Since these numbers may be too large, print them modulo 10^6 + 3. Note that A and B must be coprime before their remainders modulo 10^6 + 3 are taken. -----Examples----- Input 3 2 Output 1 8 Input 1 3 Output 1 1 Input 4 3 Output 23 128 -----Note----- In the first sample case, there are 2^3 = 8 days in Udayland. The probability that 2 people have the same birthday among 2 people is clearly $\frac{1}{8}$, so A = 1, B = 8. In the second sample case, there are only 2^1 = 2 days in Udayland, but there are 3 people, so it is guaranteed that two of them have the same birthday. Thus, the probability is 1 and A = B = 1. | C9: import math def comb(n, r): return math.gcd(math.factorial(n) // (math.factorial(r) * math.factorial(n-r)), 1000000003) n, k = map(int, input().split()) if k > (1 << n): print(-1) else: num = 1 denom = (1 << n) for i in range(1, k+1): num = (num * (denom - comb(denom, i) + comb(denom, i))) % (1000000003) print(num, denom) | D9: B | E9: https://codeforces.com/problemset/problem/711/E | F9: ## Problem ### Problem Description ZS the Coder has recently found an interesting concept called the Birthday Paradox. It states that given a random set of 23 people, there is around 50% chance that some two of them share the same birthday. ZS the Coder finds this very interesting, and decides to test this with the inhabitants of Udayland. In Udayland, there are 2^{n} days in a year. ZS the Coder wants to interview k people from Udayland, each of them has birthday in one of 2^{n} days (each day with equal probability). He is interested in the probability of at least two of them have the birthday at the same day. ZS the Coder knows that the answer can be written as an irreducible fraction $\frac{A}{B}$. He wants to find the values of A and B (he does not like to deal with floating point numbers). Can you help him? -----Input----- The first and only line of the input contains two integers n and k (1 ≤ n ≤ 10^18, 2 ≤ k ≤ 10^18), meaning that there are 2^{n} days in a year and that ZS the Coder wants to interview exactly k people. -----Output----- If the probability of at least two k people having the same birthday in 2^{n} days long year equals $\frac{A}{B}$ (A ≥ 0, B ≥ 1, $\operatorname{gcd}(A, B) = 1$), print the A and B in a single line. Since these numbers may be too large, print them modulo 10^6 + 3. Note that A and B must be coprime before their remainders modulo 10^6 + 3 are taken. -----Examples----- Input 3 2 Output 1 8 Input 1 3 Output 1 1 Input 4 3 Output 23 128 -----Note----- In the first sample case, there are 2^3 = 8 days in Udayland. The probability that 2 people have the same birthday among 2 people is clearly $\frac{1}{8}$, so A = 1, B = 8. In the second sample case, there are only 2^1 = 2 days in Udayland, but there are 3 people, so it is guaranteed that two of them have the same birthday. Thus, the probability is 1 and A = B = 1. ### Solution code file content to be Judged import math def comb(n, r): return math.gcd(math.factorial(n) // (math.factorial(r) * math.factorial(n-r)), 1000000003) n, k = map(int, input().split()) if k > (1 << n): print(-1) else: num = 1 denom = (1 << n) for i in range(1, k+1): num = (num * (denom - comb(denom, i) + comb(denom, i))) % (1000000003) print(num, denom) | G9: Mixtral | H9: 140 | I9: APPS/test/0031 | J9: {'input': '500001 1000003\n', 'expected': '256 256', 'actual': ''} | K9: B | L9: 0 AC, 0 WA, 139 CE, 0 RE, 0 TLE | M9: CE | N9: WA | O9: C | P9: STEP 1: The problem requires calculating the probability that at least two out of k people have the same birthday in a year with 2^n days. The probability should be expressed as an irreducible fraction A/B, and the result should be given modulo 10^6 + 3. STEP 2: Analyzing the code: - The function `comb(n, r)` is defined to calculate the greatest common divisor (GCD) of the binomial coefficient C(n, r) and 1000000003. However, this is not the correct use of the binomial coefficient in this context. - The input is read and split into integers n and k. - The code checks if k is greater than 2^n. If so, it prints -1. This is incorrect because the problem states that if k > 2^n, the probability is 1 (since at least two people must share a birthday). - The code initializes `num` to 1 and `denom` to 2^n. - A loop runs from 1 to k, but the logic inside the loop is incorrect. It attempts to calculate a probability using the `comb` function, which is not correctly implemented for this purpose. - Finally, it prints `num` and `denom`, but these values do not represent the correct probability. STEP 3: The code is incorrect because it does not correctly calculate the probability of at least two people sharing a birthday. The use of the `comb` function is incorrect, and the logic for calculating the probability is flawed. STEP 4: A specific test case that causes the code to fail is n = 1, k = 3. The correct output should be 1 1, but the code will not produce this result. STEP 5: The root cause of the failure is the incorrect implementation of the probability calculation. The code does not correctly handle the case where k > 2^n, and the use of the `comb` function is not appropriate for this problem. Verdict: WA (Wrong Answer) Answer: C | Q9: =_xlfn.XLOOKUP(H9,'final verdict'!F:F,'final verdict'!AJ:AJ,"") -> Misjudged compilation error as wrong answer: indentation issue
A10: 35 | B10: The flag of Berland is such rectangular field n × m that satisfies following conditions: Flag consists of three colors which correspond to letters 'R', 'G' and 'B'. Flag consists of three equal in width and height stripes, parralel to each other and to sides of the flag. Each stripe has exactly one color. Each color should be used in exactly one stripe. You are given a field n × m, consisting of characters 'R', 'G' and 'B'. Output "YES" (without quotes) if this field corresponds to correct flag of Berland. Otherwise, print "NO" (without quotes). -----Input----- The first line contains two integer numbers n and m (1 ≤ n, m ≤ 100) — the sizes of the field. Each of the following n lines consisting of m characters 'R', 'G' and 'B' — the description of the field. -----Output----- Print "YES" (without quotes) if the given field corresponds to correct flag of Berland . Otherwise, print "NO" (without quotes). -----Examples----- Input 6 5 RRRRR RRRRR BBBBB BBBBB GGGGG GGGGG Output YES Input 4 3 BRG BRG BRG BRG Output YES Input 6 7 RRRGGGG RRRGGGG RRRGGGG RRRBBBB RRRBBBB RRRBBBB Output NO Input 4 4 RRRR RRRR BBBB GGGG Output NO -----Note----- The field in the third example doesn't have three parralel stripes. Rows of the field in the fourth example are parralel to each other and to borders. But they have different heights — 2, 1 and 1. | C10: n, m = map(int, input().split()) field = [] for i in range(n): field.append(input()) def check_flag(field): flag = False for i in range(n): if field[i].count("R") == 1 and field[i].count("G") == 1 and field[i].count("B") == 1: flag = True else: flag = False break return flag def check_stripe(field): for i in range(n): if field[i].count("R") == 0 or field[i].count("G") == 0 or field[i].count("B") == 0: return False return True def check_height(field): height = 0 for i in range(n): if len(field[i]) > height: height = len(field[i]) return height def check_width(field): width = 0 for i in range(m): if len(field[i]) > width: width = len(field[i]) return width def check_color(field): for i in range(n): for j in range(m): if field[i][j] == "R" and field[i][j - 1] == "R": return False if field[i][j] == "G" and field[i][j - 1] == "G": return False if field[i][j] == "B" and field[i][j - 1] == "B": return False return True def check_stripe_height(field): for i in range(n): if field[i].count("R") == 0 or field[i].count("G") == 0 or field[i].count("B") == 0: return False return True def check_stripe_width(field): for i in range(m): if field[i].count("R") == 0 or field[i].count("G") == 0 or field[i].count("B") == 0: return False return True def check_stripe_color(field): for i in range(n): for j in range(m): if field[i][j] == "R" and field[i][j - 1] == "R": return False if field[i][j] == "G" and field[i][j - 1] == "G": return False if field[i][j] == "B" and field[i][j - 1] == "B": return False return True def check_stripe_height_width(field): for i in range(n): if len(field[i]) != height or len(field[i]) != width: return False return True def check_stripe_color_height_width(field): for i in range(n): for j in range(m): if field[i][j] == "R" and field[i][j - 1] == "R": return False if field[i][j] == "G" and field[i][j - 1] == "G": return False if field[i][j] == "B" and field[i][j - 1] == "B": return False return True def check_stripe_height_width_color(field): for i in range(n): if len(field[i]) != height or len(field[i]) != width: return False for i in range(n): for j in range(m): if field[i][j] == "R" and field[i][j - 1] == "R": return False if field[i][j] == "G" and field[i][j - 1] == "G": return False if field[i][j] == "B" and field[i][j - 1] == "B": return False return True def check_stripe_height_width_color_height_width(field): for i in range(n): if len(field[i]) != height or len(field[i]) != width: return False for i in range(n): for j in range(m): if field[i][j] == "R" and field[i][j - 1] == "R": return False if field[i][j] == "G" and field[i][j - 1] == "G": return False if field[i][j] == "B" and field[i][j - 1] == "B": return False for i in range(n): if len(field[i]) != height or len(field[i]) != width: return False return True def check_stripe_height_width_color_height_width_color(field): for i in range(n): if len(field[i]) != height or len(field[i]) != width: return False for i in range(n): for j in range(m): if field[i][j] == "R" and field[i][j - 1] == "R": return False if field[i][j] == "G" and field[i][j - 1] == "G": return False if field[i][j] == "B" and field[i][j - 1] == "B": return False for i in range(n): if len(field[i]) != height or len(field[i]) != width: return False for i in range(n): for j in range(m): if field[i][j] == "R" and field[i][j - 1] == "R": return False if field[i][j] == "G" and field[i][j - 1] == "G": return False if field[i][j] == "B" and field[i][j - 1] == "B": return False return True def check_stripe_height_width_color_height_width_color_height_width(field): for i in range(n): if len(field[i]) != height or len(field[i]) != width: return False for i in range(n): for j in range(m): if field[i][j] == "R" and field[i][j - 1] == "R": return False if field[i][j] == "G" and field[i][j - 1] == "G": return False if field[i][j] == "B" and field[i][j - 1] == "B": return False for i in range(n): if len(field[i]) != height or len(field[i]) != width: return False for i in range(n): for j in range(m): if field[i][j] == "R" and field[i][j - 1] == "R": return False if field[i][j] == "G" and field[i][j - 1] == "G": return False if field[i][j] == "B" and field[i][j - 1] == "B": return False for i in range(n): if len(field[i]) != height or len(field[i]) != width: return False for i in range(n): for j in range(m): if field[i][j] == "R" and field[i][j - 1] == "R": return False if field[i][j] == "G" and field[i][j - 1] == "G": return False if field[i][j] == "B" and field[i][j - 1] == "B": return False return True def check_stripe_height_width_color_height_width_color | D10: B | E10: https://codeforces.com/problemset/problem/837/B | F10: ## Problem ### Problem Description The flag of Berland is such rectangular field n × m that satisfies following conditions: Flag consists of three colors which correspond to letters 'R', 'G' and 'B'. Flag consists of three equal in width and height stripes, parralel to each other and to sides of the flag. Each stripe has exactly one color. Each color should be used in exactly one stripe. You are given a field n × m, consisting of characters 'R', 'G' and 'B'. Output "YES" (without quotes) if this field corresponds to correct flag of Berland. Otherwise, print "NO" (without quotes). -----Input----- The first line contains two integer numbers n and m (1 ≤ n, m ≤ 100) — the sizes of the field. Each of the following n lines consisting of m characters 'R', 'G' and 'B' — the description of the field. -----Output----- Print "YES" (without quotes) if the given field corresponds to correct flag of Berland . Otherwise, print "NO" (without quotes). -----Examples----- Input 6 5 RRRRR RRRRR BBBBB BBBBB GGGGG GGGGG Output YES Input 4 3 BRG BRG BRG BRG Output YES Input 6 7 RRRGGGG RRRGGGG RRRGGGG RRRBBBB RRRBBBB RRRBBBB Output NO Input 4 4 RRRR RRRR BBBB GGGG Output NO -----Note----- The field in the third example doesn't have three parralel stripes. Rows of the field in the fourth example are parralel to each other and to borders. But they have different heights — 2, 1 and 1. ### Solution code file content to be Judged n, m = map(int, input().split()) field = [] for i in range(n): field.append(input()) def check_flag(field): flag = False for i in range(n): if field[i].count("R") == 1 and field[i].count("G") == 1 and field[i].count("B") == 1: flag = True else: flag = False break return flag def check_stripe(field): for i in range(n): if field[i].count("R") == 0 or field[i].count("G") == 0 or field[i].count("B") == 0: return False return True def check_height(field): height = 0 for i in range(n): if len(field[i]) > height: height = len(field[i]) return height def check_width(field): width = 0 for i in range(m): if len(field[i]) > width: width = len(field[i]) return width def check_color(field): for i in range(n): for j in range(m): if field[i][j] == "R" and field[i][j - 1] == "R": return False if field[i][j] == "G" and field[i][j - 1] == "G": return False if field[i][j] == "B" and field[i][j - 1] == "B": return False return True def check_stripe_height(field): for i in range(n): if field[i].count("R") == 0 or field[i].count("G") == 0 or field[i].count("B") == 0: return False return True def check_stripe_width(field): for i in range(m): if field[i].count("R") == 0 or field[i].count("G") == 0 or field[i].count("B") == 0: return False return True def check_stripe_color(field): for i in range(n): for j in range(m): if field[i][j] == "R" and field[i][j - 1] == "R": return False if field[i][j] == "G" and field[i][j - 1] == "G": return False if field[i][j] == "B" and field[i][j - 1] == "B": return False return True def check_stripe_height_width(field): for i in range(n): if len(field[i]) != height or len(field[i]) != width: return False return True def check_stripe_color_height_width(field): for i in range(n): for j in range(m): if field[i][j] == "R" and field[i][j - 1] == "R": return False if field[i][j] == "G" and field[i][j - 1] == "G": return False if field[i][j] == "B" and field[i][j - 1] == "B": return False return True def check_stripe_height_width_color(field): for i in range(n): if len(field[i]) != height or len(field[i]) != width: return False for i in range(n): for j in range(m): if field[i][j] == "R" and field[i][j - 1] == "R": return False if field[i][j] == "G" and field[i][j - 1] == "G": return False if field[i][j] == "B" and field[i][j - 1] == "B": return False return True def check_stripe_height_width_color_height_width(field): for i in range(n): if len(field[i]) != height or len(field[i]) != width: return False for i in range(n): for j in range(m): if field[i][j] == "R" and field[i][j - 1] == "R": return False if field[i][j] == "G" and field[i][j - 1] == "G": return False if field[i][j] == "B" and field[i][j - 1] == "B": return False for i in range(n): if len(field[i]) != height or len(field[i]) != width: return False return True def check_stripe_height_width_color_height_width_color(field): for i in range(n): if len(field[i]) != height or len(field[i]) != width: return False for i in range(n): for j in range(m): if field[i][j] == "R" and field[i][j - 1] == "R": return False if field[i][j] == "G" and field[i][j - 1] == "G": return False if field[i][j] == "B" and field[i][j - 1] == "B": return False for i in range(n): if len(field[i]) != height or len(field[i]) != width: return False for i in range(n): for j in range(m): if field[i][j] == "R" and field[i][j - 1] == "R": return False if field[i][j] == "G" and field[i][j - 1] == "G": return False if field[i][j] == "B" and field[i][j - 1] == "B": return False return True def check_stripe_height_width_color_height_width_color_height_width(field): for i in range(n): if len(field[i]) != height or len(field[i]) != width: return False for i in range(n): for j in range(m): if field[i][j] == "R" and field[i][j - 1] == "R": return False if field[i][j] == "G" and field[i][j - 1] == "G": return False if field[i][j] == "B" and field[i][j - 1] == "B": return False for i in range(n): if len(field[i]) != height or len(field[i]) != width: return False for i in range(n): for j in range(m): if field[i][j] == "R" and field[i][j - 1] == "R": return False if field[i][j] == "G" and field[i][j - 1] == "G": return False if field[i][j] == "B" and field[i][j - 1] == "B": return False for i in range(n): if len(field[i]) != height or len(field[i]) != width: return False for i in range(n): for j in range(m): if field[i][j] == "R" and field[i][j - 1] == "R": return False if field[i][j] == "G" and field[i][j - 1] == "G": return False if field[i][j] == "B" and field[i][j - 1] == "B": return False return True def check_stripe_height_width_color_height_width_color | G10: codegeex | H10: 154 | I10: APPS/test/0035 | J10: {'input': '2 4\nRGBB\nRRGB\n', 'expected': 'NO\n', 'actual': ''} | K10: B | L10: 0 AC, 0 WA, 135 CE, 0 RE, 0 TLE | M10: CE | N10: WA | O10: C | P10: STEP 1: The problem requires checking if a given n x m grid of characters ('R', 'G', 'B') can represent a valid flag of Berland. The flag must have three equal-width or equal-height stripes, each of a single color, and each color must be used exactly once. STEP 2: The code attempts to solve this problem by defining multiple functions, but it is overly complex and incorrect. Let's analyze the code: - The code reads the dimensions n and m and the grid itself. - `check_flag(field)`: This function checks if each row contains exactly one 'R', one 'G', and one 'B', which is incorrect because a valid stripe should be of a single color. - `check_stripe(field)`: This function checks if each row contains at least one of each color, which is also incorrect for the same reason. - `check_height(field)` and `check_width(field)`: These functions attempt to find the maximum height and width of the field, but they are not used correctly in the context of the problem. - `check_color(field)`: This function checks if consecutive cells in a row have the same color, which is not relevant to the problem. - The remaining functions (`check_stripe_height`, `check_stripe_width`, etc.) are repetitive and incorrect, as they do not address the problem requirements. STEP 3: The code is incorrect because it does not correctly implement the logic to check for three equal-width or equal-height stripes of distinct colors. STEP 4: A test case that causes the code to fail is: ``` 3 3 RRR GGG BBB ``` Expected output: "YES" (since it forms three horizontal stripes of equal height), but the code will not produce this result. STEP 5: The root cause of the failure is that the code does not correctly check for the conditions of having three equal-width or equal-height stripes, each of a single color, and each color used exactly once. The functions are not designed to handle the problem requirements and contain logical errors. Verdict: WA (Wrong Answer) | Q10: =_xlfn.XLOOKUP(H10,'final verdict'!F:F,'final verdict'!AJ:AJ,"") -> Misjudged compilation error as wrong answer: incomplete code stops mid-generation
A11: 37 | B11: Dante is engaged in a fight with "The Savior". Before he can fight it with his sword, he needs to break its shields. He has two guns, Ebony and Ivory, each of them is able to perform any non-negative number of shots. For every bullet that hits the shield, Ebony deals a units of damage while Ivory deals b units of damage. In order to break the shield Dante has to deal exactly c units of damage. Find out if this is possible. -----Input----- The first line of the input contains three integers a, b, c (1 ≤ a, b ≤ 100, 1 ≤ c ≤ 10 000) — the number of units of damage dealt by Ebony gun and Ivory gun, and the total number of damage required to break the shield, respectively. -----Output----- Print "Yes" (without quotes) if Dante can deal exactly c damage to the shield and "No" (without quotes) otherwise. -----Examples----- Input 4 6 15 Output No Input 3 2 7 Output Yes Input 6 11 6 Output Yes -----Note----- In the second sample, Dante can fire 1 bullet from Ebony and 2 from Ivory to deal exactly 1·3 + 2·2 = 7 damage. In the third sample, Dante can fire 1 bullet from ebony and no bullets from ivory to do 1·6 + 0·11 = 6 damage. | C11: a, b, c = map(int, input().split()) for i in range(c//a + 1): j = (c - a*i) // b if a*i + b*j == c: print("Yes") break else: print("No") | D11: A | E11: https://codeforces.com/problemset/problem/633/A | F11: ## Problem ### Problem Description Dante is engaged in a fight with "The Savior". Before he can fight it with his sword, he needs to break its shields. He has two guns, Ebony and Ivory, each of them is able to perform any non-negative number of shots. For every bullet that hits the shield, Ebony deals a units of damage while Ivory deals b units of damage. In order to break the shield Dante has to deal exactly c units of damage. Find out if this is possible. -----Input----- The first line of the input contains three integers a, b, c (1 ≤ a, b ≤ 100, 1 ≤ c ≤ 10 000) — the number of units of damage dealt by Ebony gun and Ivory gun, and the total number of damage required to break the shield, respectively. -----Output----- Print "Yes" (without quotes) if Dante can deal exactly c damage to the shield and "No" (without quotes) otherwise. -----Examples----- Input 4 6 15 Output No Input 3 2 7 Output Yes Input 6 11 6 Output Yes -----Note----- In the second sample, Dante can fire 1 bullet from Ebony and 2 from Ivory to deal exactly 1·3 + 2·2 = 7 damage. In the third sample, Dante can fire 1 bullet from ebony and no bullets from ivory to do 1·6 + 0·11 = 6 damage. ### Solution code file content to be Judged a, b, c = map(int, input().split()) for i in range(c//a + 1): j = (c - a*i) // b if a*i + b*j == c: print("Yes") break else: print("No") | G11: magiccoder | H11: 162 | I11: APPS/test/0037 | K11: A | L11: 134 AC, 0 WA, 0 CE, 0 RE, 0 TLE | M11: AC | N11: WA | O11: C | P11: STEP 1: The problem requires determining if it's possible to achieve exactly 'c' units of damage using two types of guns, where one gun deals 'a' units of damage per shot and the other deals 'b' units per shot. The task is to find non-negative integers i and j such that a*i + b*j = c. STEP 2: The code begins by reading the integers a, b, and c from input. It then iterates over possible values of i, which represents the number of shots from the first gun (Ebony). The loop runs from 0 to c//a, inclusive, which covers all possible numbers of shots from the first gun that do not exceed the required damage c. For each i, it calculates j as (c - a*i) // b, which is the number of shots from the second gun (Ivory) needed to make up the remaining damage. The code checks if a*i + b*j equals c. If it does, it prints 'Yes' and breaks out of the loop. If the loop completes without finding a solution, it prints 'No'. STEP 3: The code is incorrect. The logic for calculating j is flawed because it uses integer division, which can lead to incorrect results when the remainder is not zero. This means that the condition a*i + b*j == c may not be satisfied even if a valid solution exists. STEP 4: A specific test case that causes the code to fail is a = 4, b = 6, c = 14. The correct answer is 'Yes' because 2 shots from Ebony (2*4 = 8) and 1 shot from Ivory (1*6 = 6) sum to 14. However, the code will output 'No'. STEP 5: The root cause of the failure is the use of integer division to calculate j. This approach does not account for the possibility that the remainder of (c - a*i) when divided by b is non-zero, which can still allow for a valid solution if the remainder is zero when added to a*i. The code should instead check if (c - a*i) % b == 0 to determine if a valid j exists. | Q11: =_xlfn.XLOOKUP(H11,'final verdict'!F:F,'final verdict'!AJ:AJ,"") -> Misjudged correct as wrong answer: rationale is incorrect (reason: judge predicted a wrong expected output)
A12: 37 | B12: Dante is engaged in a fight with "The Savior". Before he can fight it with his sword, he needs to break its shields. He has two guns, Ebony and Ivory, each of them is able to perform any non-negative number of shots. For every bullet that hits the shield, Ebony deals a units of damage while Ivory deals b units of damage. In order to break the shield Dante has to deal exactly c units of damage. Find out if this is possible. -----Input----- The first line of the input contains three integers a, b, c (1 ≤ a, b ≤ 100, 1 ≤ c ≤ 10 000) — the number of units of damage dealt by Ebony gun and Ivory gun, and the total number of damage required to break the shield, respectively. -----Output----- Print "Yes" (without quotes) if Dante can deal exactly c damage to the shield and "No" (without quotes) otherwise. -----Examples----- Input 4 6 15 Output No Input 3 2 7 Output Yes Input 6 11 6 Output Yes -----Note----- In the second sample, Dante can fire 1 bullet from Ebony and 2 from Ivory to deal exactly 1·3 + 2·2 = 7 damage. In the third sample, Dante can fire 1 bullet from ebony and no bullets from ivory to do 1·6 + 0·11 = 6 damage. | C12: a, b, c = map(int, input().split()) for i in range(c + 1): if (c - i * a) % b == 0: print("Yes") exit(0) print("No") | D12: C | E12: https://codeforces.com/problemset/problem/633/A | F12: ## Problem ### Problem Description Dante is engaged in a fight with "The Savior". Before he can fight it with his sword, he needs to break its shields. He has two guns, Ebony and Ivory, each of them is able to perform any non-negative number of shots. For every bullet that hits the shield, Ebony deals a units of damage while Ivory deals b units of damage. In order to break the shield Dante has to deal exactly c units of damage. Find out if this is possible. -----Input----- The first line of the input contains three integers a, b, c (1 ≤ a, b ≤ 100, 1 ≤ c ≤ 10 000) — the number of units of damage dealt by Ebony gun and Ivory gun, and the total number of damage required to break the shield, respectively. -----Output----- Print "Yes" (without quotes) if Dante can deal exactly c damage to the shield and "No" (without quotes) otherwise. -----Examples----- Input 4 6 15 Output No Input 3 2 7 Output Yes Input 6 11 6 Output Yes -----Note----- In the second sample, Dante can fire 1 bullet from Ebony and 2 from Ivory to deal exactly 1·3 + 2·2 = 7 damage. In the third sample, Dante can fire 1 bullet from ebony and no bullets from ivory to do 1·6 + 0·11 = 6 damage. ### Solution code file content to be Judged a, b, c = map(int, input().split()) for i in range(c + 1): if (c - i * a) % b == 0: print("Yes") exit(0) print("No") | G12: qwen | H12: 163 | I12: APPS/test/0037 | J12: {'input': '10 8 2\n', 'expected': 'No\n', 'actual': 'Yes\n'} | K12: C | L12: 110 AC, 24 WA, 0 CE, 0 RE, 0 TLE | M12: WA | N12: AC | O12: A | P12: STEP 1: The problem requires determining if it's possible to achieve exactly 'c' units of damage using two types of guns, where one gun deals 'a' units of damage per shot and the other deals 'b' units per shot. The task is to find non-negative integers x and y such that x * a + y * b = c. STEP 2: The code begins by reading three integers a, b, and c from input. It then iterates over all possible values of x (from 0 to c) to check if there exists a non-negative integer y such that the equation x * a + y * b = c holds true. This is done by checking if (c - i * a) is divisible by b, which would imply that y is a non-negative integer. If such a y is found, the code prints 'Yes' and exits. If the loop completes without finding such a pair (x, y), it prints 'No'. STEP 3: The code is correct. It correctly implements the logic to check for the existence of non-negative integers x and y that satisfy the equation x * a + y * b = c. The loop iterates over all possible values of x, and for each x, it checks if the remaining damage (c - i * a) can be exactly divided by b, which would mean y is a non-negative integer. STEP 4: Not applicable as the code is correct. STEP 5: Not applicable as the code is correct. The code correctly solves the problem by checking all possible combinations of shots from the two guns to achieve the exact damage required. | Q12: =_xlfn.XLOOKUP(H12,'final verdict'!F:F,'final verdict'!AJ:AJ,"") -> Misjudged wrong answer as correct: wrong answer on many cases but correct on a majority
A13: 38 | B13: Running with barriers on the circle track is very popular in the country where Dasha lives, so no wonder that on her way to classes she saw the following situation: The track is the circle with length L, in distinct points of which there are n barriers. Athlete always run the track in counterclockwise direction if you look on him from above. All barriers are located at integer distance from each other along the track. Her friends the parrot Kefa and the leopard Sasha participated in competitions and each of them ran one lap. Each of the friends started from some integral point on the track. Both friends wrote the distance from their start along the track to each of the n barriers. Thus, each of them wrote n integers in the ascending order, each of them was between 0 and L - 1, inclusively. [Image] Consider an example. Let L = 8, blue points are barriers, and green points are Kefa's start (A) and Sasha's start (B). Then Kefa writes down the sequence [2, 4, 6], and Sasha writes down [1, 5, 7]. There are several tracks in the country, all of them have same length and same number of barriers, but the positions of the barriers can differ among different tracks. Now Dasha is interested if it is possible that Kefa and Sasha ran the same track or they participated on different tracks. Write the program which will check that Kefa's and Sasha's tracks coincide (it means that one can be obtained from the other by changing the start position). Note that they always run the track in one direction — counterclockwise, if you look on a track from above. -----Input----- The first line contains two integers n and L (1 ≤ n ≤ 50, n ≤ L ≤ 100) — the number of barriers on a track and its length. The second line contains n distinct integers in the ascending order — the distance from Kefa's start to each barrier in the order of its appearance. All integers are in the range from 0 to L - 1 inclusively. The second line contains n distinct integers in the ascending order — the distance from Sasha's start to each barrier in the order of its overcoming. All integers are in the range from 0 to L - 1 inclusively. -----Output----- Print "YES" (without quotes), if Kefa and Sasha ran the coinciding tracks (it means that the position of all barriers coincides, if they start running from the same points on the track). Otherwise print "NO" (without quotes). -----Examples----- Input 3 8 2 4 6 1 5 7 Output YES Input 4 9 2 3 5 8 0 1 3 6 Output YES Input 2 4 1 3 1 2 Output NO -----Note----- The first test is analyzed in the statement. | C13: n, L = map(int, input().split()) a = list(map(int, input().split())) b = list(map(int, input().split())) a += [x + L for x in a] for i in range(n): if a[i:i + n] == b: print("YES") exit(0) print("NO") | D13: C | E13: https://codeforces.com/problemset/problem/761/B | F13: ## Problem ### Problem Description Running with barriers on the circle track is very popular in the country where Dasha lives, so no wonder that on her way to classes she saw the following situation: The track is the circle with length L, in distinct points of which there are n barriers. Athlete always run the track in counterclockwise direction if you look on him from above. All barriers are located at integer distance from each other along the track. Her friends the parrot Kefa and the leopard Sasha participated in competitions and each of them ran one lap. Each of the friends started from some integral point on the track. Both friends wrote the distance from their start along the track to each of the n barriers. Thus, each of them wrote n integers in the ascending order, each of them was between 0 and L - 1, inclusively. [Image] Consider an example. Let L = 8, blue points are barriers, and green points are Kefa's start (A) and Sasha's start (B). Then Kefa writes down the sequence [2, 4, 6], and Sasha writes down [1, 5, 7]. There are several tracks in the country, all of them have same length and same number of barriers, but the positions of the barriers can differ among different tracks. Now Dasha is interested if it is possible that Kefa and Sasha ran the same track or they participated on different tracks. Write the program which will check that Kefa's and Sasha's tracks coincide (it means that one can be obtained from the other by changing the start position). Note that they always run the track in one direction — counterclockwise, if you look on a track from above. -----Input----- The first line contains two integers n and L (1 ≤ n ≤ 50, n ≤ L ≤ 100) — the number of barriers on a track and its length. The second line contains n distinct integers in the ascending order — the distance from Kefa's start to each barrier in the order of its appearance. All integers are in the range from 0 to L - 1 inclusively. The second line contains n distinct integers in the ascending order — the distance from Sasha's start to each barrier in the order of its overcoming. All integers are in the range from 0 to L - 1 inclusively. -----Output----- Print "YES" (without quotes), if Kefa and Sasha ran the coinciding tracks (it means that the position of all barriers coincides, if they start running from the same points on the track). Otherwise print "NO" (without quotes). -----Examples----- Input 3 8 2 4 6 1 5 7 Output YES Input 4 9 2 3 5 8 0 1 3 6 Output YES Input 2 4 1 3 1 2 Output NO -----Note----- The first test is analyzed in the statement. ### Solution code file content to be Judged n, L = map(int, input().split()) a = list(map(int, input().split())) b = list(map(int, input().split())) a += [x + L for x in a] for i in range(n): if a[i:i + n] == b: print("YES") exit(0) print("NO") | G13: gpt4 | H13: 164 | I13: APPS/test/0038 | J13: {'input': '47 49\n0 1 2 3 4 5 6 7 9 10 11 12 13 14 15 16 18 19 20 21 22 23 24 25 26 27 28 29 30 31 32 33 34 35 36 37 38 39 40 41 42 43 44 45 46 47 48\n0 1 2 3 4 5 6 7 8 9 10 11 13 14 15 16 17 18 19 20 22 23 24 25 26 27 28 29 30 31 32 33 34 35 36 37 38 39 40 41 42 43 44 45 46 47 48\n', 'expected': 'YES\n', 'actual': 'NO\n'} | K13: C | L13: 34 AC, 100 WA, 0 CE, 0 RE, 0 TLE | M13: WA | N13: AC | O13: A | P13: STEP 1: The problem requires determining if two athletes, Kefa and Sasha, ran on the same circular track with barriers, given their recorded distances to the barriers. The track is circular with length L, and each athlete records the distances to n barriers in ascending order. The task is to check if one sequence of distances can be obtained from the other by changing the starting point on the track. STEP 2: The code begins by reading the input values for n (number of barriers) and L (length of the track). It then reads two lists, a and b, which represent the distances from Kefa's and Sasha's starting points to the barriers, respectively. The code extends list a by appending each element of a incremented by L, effectively simulating the circular nature of the track. This allows for checking if b can be found as a contiguous subarray within this extended list a. The code iterates over possible starting points in a and checks if the subarray from that point matches b. If a match is found, it prints 'YES' and exits. If no match is found after checking all possible starting points, it prints 'NO'. STEP 3: The code is correct. It correctly simulates the circular nature of the track by extending the list a and checks for all possible starting points to see if b can be obtained from a by a circular shift. STEP 4: Not applicable as the code is correct. STEP 5: Not applicable as the code is correct. The code correctly implements the logic to determine if the two sequences of barrier distances can represent the same track by considering circular shifts. | Q13: =_xlfn.XLOOKUP(H13,'final verdict'!F:F,'final verdict'!AJ:AJ,"") -> Misjudged wrong answer as correct: wrong answer for most tests
A14: 40 | B14: Is it rated? Here it is. The Ultimate Question of Competitive Programming, Codeforces, and Everything. And you are here to answer it. Another Codeforces round has been conducted. No two participants have the same number of points. For each participant, from the top to the bottom of the standings, their rating before and after the round is known. It's known that if at least one participant's rating has changed, then the round was rated for sure. It's also known that if the round was rated and a participant with lower rating took a better place in the standings than a participant with higher rating, then at least one round participant's rating has changed. In this problem, you should not make any other assumptions about the rating system. Determine if the current round is rated, unrated, or it's impossible to determine whether it is rated of not. -----Input----- The first line contains a single integer n (2 ≤ n ≤ 1000) — the number of round participants. Each of the next n lines contains two integers a_{i} and b_{i} (1 ≤ a_{i}, b_{i} ≤ 4126) — the rating of the i-th participant before and after the round, respectively. The participants are listed in order from the top to the bottom of the standings. -----Output----- If the round is rated for sure, print "rated". If the round is unrated for sure, print "unrated". If it's impossible to determine whether the round is rated or not, print "maybe". -----Examples----- Input 6 3060 3060 2194 2194 2876 2903 2624 2624 3007 2991 2884 2884 Output rated Input 4 1500 1500 1300 1300 1200 1200 1400 1400 Output unrated Input 5 3123 3123 2777 2777 2246 2246 2246 2246 1699 1699 Output maybe -----Note----- In the first example, the ratings of the participants in the third and fifth places have changed, therefore, the round was rated. In the second example, no one's rating has changed, but the participant in the second place has lower rating than the participant in the fourth place. Therefore, if the round was rated, someone's rating would've changed for sure. In the third example, no one's rating has changed, and the participants took places in non-increasing order of their rating. Therefore, it's impossible to determine whether the round is rated or not. | C14: block # Initialize a list to store the participants' ratings before and after the round participants_ratings = [] for _ in range(n): participants_ratings.append([0, 0]) # Iterate through the participants and update their ratings for i in range(n): participants_ratings[i][1] = int(input()) # Check if at least one participant's rating has changed changed_rating = False for i in range(n): if participants_ratings[i][1] != participants_ratings[i][0]: changed_rating = True break if not changed_rating: return "maybe" # Check if a participant with lower rating took a better place in the standings than a participant with higher rating better_place = False for i in range(n): if participants_ratings[i][1] < participants_ratings[i-1][1]: better_place = True break if better_place: return "unrated" return "rated" # Test the function with some sample inputs print(is_rated(6)) # Output: rated print(is_rated(4)) # Output: unrated print(is_rated(5)) # Output: maybe | D14: B | E14: https://codeforces.com/problemset/problem/807/A | F14: ## Problem ### Problem Description Is it rated? Here it is. The Ultimate Question of Competitive Programming, Codeforces, and Everything. And you are here to answer it. Another Codeforces round has been conducted. No two participants have the same number of points. For each participant, from the top to the bottom of the standings, their rating before and after the round is known. It's known that if at least one participant's rating has changed, then the round was rated for sure. It's also known that if the round was rated and a participant with lower rating took a better place in the standings than a participant with higher rating, then at least one round participant's rating has changed. In this problem, you should not make any other assumptions about the rating system. Determine if the current round is rated, unrated, or it's impossible to determine whether it is rated of not. -----Input----- The first line contains a single integer n (2 ≤ n ≤ 1000) — the number of round participants. Each of the next n lines contains two integers a_{i} and b_{i} (1 ≤ a_{i}, b_{i} ≤ 4126) — the rating of the i-th participant before and after the round, respectively. The participants are listed in order from the top to the bottom of the standings. -----Output----- If the round is rated for sure, print "rated". If the round is unrated for sure, print "unrated". If it's impossible to determine whether the round is rated or not, print "maybe". -----Examples----- Input 6 3060 3060 2194 2194 2876 2903 2624 2624 3007 2991 2884 2884 Output rated Input 4 1500 1500 1300 1300 1200 1200 1400 1400 Output unrated Input 5 3123 3123 2777 2777 2246 2246 2246 2246 1699 1699 Output maybe -----Note----- In the first example, the ratings of the participants in the third and fifth places have changed, therefore, the round was rated. In the second example, no one's rating has changed, but the participant in the second place has lower rating than the participant in the fourth place. Therefore, if the round was rated, someone's rating would've changed for sure. In the third example, no one's rating has changed, and the participants took places in non-increasing order of their rating. Therefore, it's impossible to determine whether the round is rated or not. ### Solution code file content to be Judged block # Initialize a list to store the participants' ratings before and after the round participants_ratings = [] for _ in range(n): participants_ratings.append([0, 0]) # Iterate through the participants and update their ratings for i in range(n): participants_ratings[i][1] = int(input()) # Check if at least one participant's rating has changed changed_rating = False for i in range(n): if participants_ratings[i][1] != participants_ratings[i][0]: changed_rating = True break if not changed_rating: return "maybe" # Check if a participant with lower rating took a better place in the standings than a participant with higher rating better_place = False for i in range(n): if participants_ratings[i][1] < participants_ratings[i-1][1]: better_place = True break if better_place: return "unrated" return "rated" # Test the function with some sample inputs print(is_rated(6)) # Output: rated print(is_rated(4)) # Output: unrated print(is_rated(5)) # Output: maybe | G14: llama | H14: 173 | I14: APPS/test/0040 | J14: {'input': '2\n4 4\n3 3\n', 'expected': 'maybe\n', 'actual': ''} | K14: B | L14: 0 AC, 0 WA, 132 CE, 0 RE, 0 TLE | M14: CE | N14: WA | O14: C | P14: STEP 1: The problem requires determining if a competitive programming round is rated, unrated, or indeterminate ('maybe'). The round is rated if any participant's rating changes. If no ratings change, but the standings are not in non-increasing order of ratings, the round is unrated. Otherwise, it's 'maybe'. STEP 2: Analyzing the code: - The code initializes a list `participants_ratings` to store ratings before and after the round. - It attempts to populate this list with input values, but only assigns values to `participants_ratings[i][1]`, leaving `participants_ratings[i][0]` as 0. - It checks if any rating has changed by comparing `participants_ratings[i][1]` with `participants_ratings[i][0]`, which will always be false since `participants_ratings[i][0]` is 0. - If no ratings have changed, it returns 'maybe'. - It checks if the standings are not in non-increasing order by comparing `participants_ratings[i][1]` with `participants_ratings[i-1][1]`, but this logic is flawed as it doesn't correctly handle the first element and doesn't compare the correct values. - If the standings are not in order, it returns 'unrated'. - If neither condition is met, it returns 'rated'. STEP 3: The code is incorrect because it doesn't correctly populate the initial ratings and fails to properly check the conditions for 'unrated'. STEP 4: A test case that causes failure: Input: 3 1500 1500 1400 1400 1300 1300 Expected Output: 'maybe' Actual Output: 'maybe' (but due to incorrect logic, not because of correct checks) STEP 5: The root cause of the failure is that the code doesn't correctly populate the initial ratings and doesn't properly check the conditions for 'unrated'. The logic for checking if the standings are in non-increasing order is flawed, and the initial ratings are not read from input, leading to incorrect comparisons. | Q14: =_xlfn.XLOOKUP(H14,'final verdict'!F:F,'final verdict'!AJ:AJ,"") -> Misjudged compilation error as wrong answer: return statement used outside of function
A15: 41 | B15: You are given the array of integer numbers a_0, a_1, ..., a_{n} - 1. For each element find the distance to the nearest zero (to the element which equals to zero). There is at least one zero element in the given array. -----Input----- The first line contains integer n (1 ≤ n ≤ 2·10^5) — length of the array a. The second line contains integer elements of the array separated by single spaces ( - 10^9 ≤ a_{i} ≤ 10^9). -----Output----- Print the sequence d_0, d_1, ..., d_{n} - 1, where d_{i} is the difference of indices between i and nearest j such that a_{j} = 0. It is possible that i = j. -----Examples----- Input 9 2 1 0 3 0 0 3 2 4 Output 2 1 0 1 0 0 1 2 3 Input 5 0 1 2 3 4 Output 0 1 2 3 4 Input 7 5 6 0 1 -2 3 4 Output 2 1 0 1 2 3 4 | C15: n = int(input()) arr = list(map(int, input().split())) left_zero = -1 right_zero = n result = [0] * n for i in range(n): if arr[i] == 0: left_zero = i result[i] = i - left_zero for i in range(n - 1, -1, -1): if arr[i] == 0: right_zero = i result[i] = min(result[i], right_zero - i) print(*result) | D15: C | E15: https://codeforces.com/problemset/problem/803/B | F15: ## Problem ### Problem Description You are given the array of integer numbers a_0, a_1, ..., a_{n} - 1. For each element find the distance to the nearest zero (to the element which equals to zero). There is at least one zero element in the given array. -----Input----- The first line contains integer n (1 ≤ n ≤ 2·10^5) — length of the array a. The second line contains integer elements of the array separated by single spaces ( - 10^9 ≤ a_{i} ≤ 10^9). -----Output----- Print the sequence d_0, d_1, ..., d_{n} - 1, where d_{i} is the difference of indices between i and nearest j such that a_{j} = 0. It is possible that i = j. -----Examples----- Input 9 2 1 0 3 0 0 3 2 4 Output 2 1 0 1 0 0 1 2 3 Input 5 0 1 2 3 4 Output 0 1 2 3 4 Input 7 5 6 0 1 -2 3 4 Output 2 1 0 1 2 3 4 ### Solution code file content to be Judged n = int(input()) arr = list(map(int, input().split())) left_zero = -1 right_zero = n result = [0] * n for i in range(n): if arr[i] == 0: left_zero = i result[i] = i - left_zero for i in range(n - 1, -1, -1): if arr[i] == 0: right_zero = i result[i] = min(result[i], right_zero - i) print(*result) | G15: gpt3.5 | H15: 174 | I15: APPS/test/0041 | J15: {'input': '8\n-1000000000 -1000000000 -1000000000 -1000000000 0 0 0 0\n', 'expected': '4 3 2 1 0 0 0 0 ', 'actual': '1 2 2 1 0 0 0 0\n'} | K15: C | L15: 63 AC, 69 WA, 0 CE, 0 RE, 0 TLE | M15: WA | N15: AC | O15: A | P15: STEP 1: The problem requires finding the distance of each element in an array to the nearest zero. The array is guaranteed to have at least one zero, and the output should be the sequence of these distances. STEP 2: The code begins by reading the input values: the length of the array `n` and the array `arr` itself. It initializes two variables, `left_zero` and `right_zero`, to track the positions of the nearest zeros to the left and right of the current element, respectively. `left_zero` is initialized to -1, indicating no zero has been found to the left initially, and `right_zero` is initialized to `n`, a value beyond the last index, indicating no zero has been found to the right initially. The `result` array is initialized with zeros, which will store the minimum distances to the nearest zero for each element. The first loop iterates over the array from left to right. If a zero is found at index `i`, `left_zero` is updated to `i`. The distance from the current index `i` to the nearest zero on the left is calculated as `i - left_zero` and stored in `result[i]`. The second loop iterates over the array from right to left. If a zero is found at index `i`, `right_zero` is updated to `i`. The distance from the current index `i` to the nearest zero on the right is calculated as `right_zero - i`. The minimum of the current value in `result[i]` and this new distance is stored back in `result[i]`. Finally, the `result` array is printed, which contains the minimum distances to the nearest zero for each element. STEP 3: The code is correct. It correctly calculates the minimum distance to the nearest zero for each element by considering both left and right directions. STEP 4: Not applicable as the code is correct. STEP 5: Not applicable as the code is correct. | Q15: =_xlfn.XLOOKUP(H15,'final verdict'!F:F,'final verdict'!AJ:AJ,"") -> Misjudged wrong answer as correct: wrong answer for about half of the tests
A16: 45 | B16: You are given positive integer number n. You should create such strictly increasing sequence of k positive numbers a_1, a_2, ..., a_{k}, that their sum is equal to n and greatest common divisor is maximal. Greatest common divisor of sequence is maximum of such numbers that every element of sequence is divisible by them. If there is no possible sequence then output -1. -----Input----- The first line consists of two numbers n and k (1 ≤ n, k ≤ 10^10). -----Output----- If the answer exists then output k numbers — resulting sequence. Otherwise output -1. If there are multiple answers, print any of them. -----Examples----- Input 6 3 Output 1 2 3 Input 8 2 Output 2 6 Input 5 3 Output -1 | C16: print(find_greatest_common_divisor(6, 3)) # Output: [1, 2, 3] print(find_greatest_common_divisor(8, 2)) # Output: [2, 6] print(find_greatest_common_divisor(5, 3)) # Output: -1 | D16: C | E16: https://codeforces.com/problemset/problem/803/C | F16: ## Problem ### Problem Description You are given positive integer number n. You should create such strictly increasing sequence of k positive numbers a_1, a_2, ..., a_{k}, that their sum is equal to n and greatest common divisor is maximal. Greatest common divisor of sequence is maximum of such numbers that every element of sequence is divisible by them. If there is no possible sequence then output -1. -----Input----- The first line consists of two numbers n and k (1 ≤ n, k ≤ 10^10). -----Output----- If the answer exists then output k numbers — resulting sequence. Otherwise output -1. If there are multiple answers, print any of them. -----Examples----- Input 6 3 Output 1 2 3 Input 8 2 Output 2 6 Input 5 3 Output -1 ### Solution code file content to be Judged print(find_greatest_common_divisor(6, 3)) # Output: [1, 2, 3] print(find_greatest_common_divisor(8, 2)) # Output: [2, 6] print(find_greatest_common_divisor(5, 3)) # Output: -1 | G16: llama | H16: 191 | I16: APPS/test/0045 | J16: {'input': '8 10\n', 'expected': '-1\n', 'actual': ''} | K16: C | L16: 0 AC, 0 WA, 0 CE, 129 RE, 0 TLE | M16: RE | N16: CE | O16: B | P16: STEP 1: The problem requires finding a strictly increasing sequence of k positive integers whose sum is n and whose greatest common divisor (GCD) is maximized. If no such sequence exists, the output should be -1. The constraints are that n and k are both positive integers up to 10^10. STEP 2: The provided code snippet does not contain the implementation of the function `find_greatest_common_divisor`. Instead, it only contains calls to this function with example inputs and expected outputs as comments. This indicates that the actual logic for solving the problem is missing. STEP 3: The code is incorrect because it lacks the implementation of the function `find_greatest_common_divisor`. Without this function, the code cannot produce any output, let alone the correct one. STEP 4: Since the code is missing the implementation, any input will cause it to fail. For example, the input (6, 3) will not produce the expected output [1, 2, 3] because the function is not defined. STEP 5: The root cause of the failure is the absence of the function `find_greatest_common_divisor`. Without this function, the code cannot execute and solve the problem as intended. | Q16: =_xlfn.XLOOKUP(H16,'final verdict'!F:F,'final verdict'!AJ:AJ,"") -> Misjudged runtime error as compilation error: non-existent function called, leads to runtime error
A17: 48 | B17: Bizon the Champion isn't just charming, he also is very smart. While some of us were learning the multiplication table, Bizon the Champion had fun in his own manner. Bizon the Champion painted an n × m multiplication table, where the element on the intersection of the i-th row and j-th column equals i·j (the rows and columns of the table are numbered starting from 1). Then he was asked: what number in the table is the k-th largest number? Bizon the Champion always answered correctly and immediately. Can you repeat his success? Consider the given multiplication table. If you write out all n·m numbers from the table in the non-decreasing order, then the k-th number you write out is called the k-th largest number. -----Input----- The single line contains integers n, m and k (1 ≤ n, m ≤ 5·10^5; 1 ≤ k ≤ n·m). -----Output----- Print the k-th largest number in a n × m multiplication table. -----Examples----- Input 2 2 2 Output 2 Input 2 3 4 Output 3 Input 1 10 5 Output 5 -----Note----- A 2 × 3 multiplication table looks like this: 1 2 3 2 4 6 | C17: n, m, k = map(int, input().split()) def count_less_equal(x): count = 0 for i in range(1, n+1): count += min(x // i, m) return count left, right = 1, n*m while left < right: mid = (left + right) // 2 if count_less_equal(mid) < k: left = mid + 1 else: right = mid print(left) | D17: C | E17: https://codeforces.com/problemset/problem/448/D | F17: ## Problem ### Problem Description Bizon the Champion isn't just charming, he also is very smart. While some of us were learning the multiplication table, Bizon the Champion had fun in his own manner. Bizon the Champion painted an n × m multiplication table, where the element on the intersection of the i-th row and j-th column equals i·j (the rows and columns of the table are numbered starting from 1). Then he was asked: what number in the table is the k-th largest number? Bizon the Champion always answered correctly and immediately. Can you repeat his success? Consider the given multiplication table. If you write out all n·m numbers from the table in the non-decreasing order, then the k-th number you write out is called the k-th largest number. -----Input----- The single line contains integers n, m and k (1 ≤ n, m ≤ 5·10^5; 1 ≤ k ≤ n·m). -----Output----- Print the k-th largest number in a n × m multiplication table. -----Examples----- Input 2 2 2 Output 2 Input 2 3 4 Output 3 Input 1 10 5 Output 5 -----Note----- A 2 × 3 multiplication table looks like this: 1 2 3 2 4 6 ### Solution code file content to be Judged n, m, k = map(int, input().split()) def count_less_equal(x): count = 0 for i in range(1, n+1): count += min(x // i, m) return count left, right = 1, n*m while left < right: mid = (left + right) // 2 if count_less_equal(mid) < k: left = mid + 1 else: right = mid print(left) | G17: gpt3.5 | H17: 203 | I17: APPS/test/0048 | J17: {'input': '500000 500000 888888\n', 'expected': '77856\n', 'actual': ''} | K17: C | L17: 104 AC, 0 WA, 0 CE, 0 RE, 23 TLE | M17: TLE | N17: AC | O17: A | P17: STEP 1: The problem requires finding the k-th largest number in an n x m multiplication table, where each element at position (i, j) is the product i * j. The constraints are large, with n and m up to 500,000, so an efficient solution is necessary. The task is to output the k-th largest number when all elements are sorted in non-decreasing order. STEP 2: The code begins by reading the integers n, m, and k from input. It defines a helper function `count_less_equal(x)` that counts how many numbers in the multiplication table are less than or equal to x. This is done by iterating over each row i and counting the number of elements in that row that are less than or equal to x, which is `min(x // i, m)`. The main logic uses binary search to find the k-th largest number. It initializes `left` to 1 and `right` to n*m (the maximum possible value in the table). The binary search continues until `left` is equal to `right`. In each iteration, it calculates `mid` as the average of `left` and `right`. If the count of numbers less than or equal to `mid` is less than k, it means the k-th largest number is greater than `mid`, so it sets `left` to `mid + 1`. Otherwise, it sets `right` to `mid`. Finally, it prints `left`, which is the k-th largest number. STEP 3: The code is correct. It efficiently finds the k-th largest number using binary search and a counting function, which is appropriate given the constraints. STEP 4: Not applicable as the code is correct. STEP 5: Not applicable as the code is correct. | Q17: =_xlfn.XLOOKUP(H17,'final verdict'!F:F,'final verdict'!AJ:AJ,"") -> Misjudged time limit exceeded as correct: solution is not efficient
A18: 52 | B18: Daniel is organizing a football tournament. He has come up with the following tournament format: In the first several (possibly zero) stages, while the number of teams is even, they split in pairs and play one game for each pair. At each stage the loser of each pair is eliminated (there are no draws). Such stages are held while the number of teams is even. Eventually there will be an odd number of teams remaining. If there is one team remaining, it will be declared the winner, and the tournament ends. Otherwise each of the remaining teams will play with each other remaining team once in round robin tournament (if there are x teams, there will be $\frac{x \cdot(x - 1)}{2}$ games), and the tournament ends. For example, if there were 20 teams initially, they would begin by playing 10 games. So, 10 teams would be eliminated, and the remaining 10 would play 5 games. Then the remaining 5 teams would play 10 games in a round robin tournament. In total there would be 10+5+10=25 games. Daniel has already booked the stadium for n games. Help him to determine how many teams he should invite so that the tournament needs exactly n games. You should print all possible numbers of teams that will yield exactly n games in ascending order, or -1 if there are no such numbers. -----Input----- The first line contains a single integer n (1 ≤ n ≤ 10^18), the number of games that should be played. Please, do not use the %lld specifier to read or write 64-bit integers in С++. It is preferred to use the cin, cout streams or the %I64d specifier. -----Output----- Print all possible numbers of invited teams in ascending order, one per line. If exactly n games cannot be played, output one number: -1. -----Examples----- Input 3 Output 3 4 Input 25 Output 20 Input 2 Output -1 | C18: import sys n = int(sys.stdin.readline()) def is_possible(x): if x % 2 == 0: return True else: return False def is_possible_2(x): if x % 2 == 0: return True else: return False def is_possible_3(x): if x % 2 == 0: return True else: return False def is_possible_4(x): if x % 2 == 0: return True else: return False def is_possible_5(x): if x % 2 == 0: return True else: return False def is_possible_6(x): if x % 2 == 0: return True else: return False def is_possible_7(x): if x % 2 == 0: return True else: return False def is_possible_8(x): if x % 2 == 0: return True else: return False def is_possible_9(x): if x % 2 == 0: return True else: return False def is_possible_10(x): if x % 2 == 0: return True else: return False def is_possible_11(x): if x % 2 == 0: return True else: return False def is_possible_12(x): if x % 2 == 0: return True else: return False def is_possible_13(x): if x % 2 == 0: return True else: return False def is_possible_14(x): if x % 2 == 0: return True else: return False def is_possible_15(x): if x % 2 == 0: return True else: return False def is_possible_16(x): if x % 2 == 0: return True else: return False def is_possible_17(x): if x % 2 == 0: return True else: return False def is_possible_18(x): if x % 2 == 0: return True else: return False def is_possible_19(x): if x % 2 == 0: return True else: return False def is_possible_20(x): if x % 2 == 0: return True else: return False def is_possible_21(x): if x % 2 == 0: return True else: return False def is_possible_22(x): if x % 2 == 0: return True else: return False def is_possible_23(x): if x % 2 == 0: return True else: return False def is_possible_24(x): if x % 2 == 0: return True else: return False def is_possible_25(x): if x % 2 == 0: return True else: return False def is_possible_26(x): if x % 2 == 0: return True else: return False def is_possible_27(x): if x % 2 == 0: return True else: return False def is_possible_28(x): if x % 2 == 0: return True else: return False def is_possible_29(x): if x % 2 == 0: return True else: return False def is_possible_30(x): if x % 2 == 0: return True else: return False def is_possible_31(x): if x % 2 == 0: return True else: return False def is_possible_32(x): if x % 2 == 0: return True else: return False def is_possible_33(x): if x % 2 == 0: return True else: return False def is_possible_34(x): if x % 2 == 0: return True else: return False def is_possible_35(x): if x % 2 == 0: return True else: return False def is_possible_36(x): if x % 2 == 0: return True else: return False def is_possible_37(x): if x % 2 == 0: return True else: return False def is_possible_38(x): if x % 2 == 0: return True else: return False def is_possible_39(x): if x % 2 == 0: return True else: return False def is_possible_40(x): if x % 2 == 0: return True else: return False def is_possible_41(x): if x % 2 == 0: return True else: return False def is_possible_42(x): if x % 2 == 0: return True else: return False def is_possible_43(x): if x % 2 == 0: return True else: return False def is_possible_44(x): if x % 2 == 0: return True else: return False def is_possible_45(x): if x % 2 == 0: return True else: return False def is_possible_46(x): if x % 2 == 0: return True else: return False def is_possible_47(x): if x % 2 == 0: return True else: return False def is_possible_48(x): if x % 2 == 0: return True else: return False def is_possible_49(x): if x % 2 == 0: return True else: return False def is_possible_50(x): if x % 2 == 0: return True else: return False def is_possible_51(x): if x % 2 == 0: return True else: return False def is_possible_52(x): if x % 2 == 0: return True else: return False def is_possible_53(x): if x % 2 == 0: return True else: return False def is_possible_54(x): if x % 2 == 0: return True else: return False def is_possible_55(x): if x % 2 == 0: return True else: return False def is_possible | D18: B | E18: https://codeforces.com/problemset/problem/325/B | F18: ## Problem ### Problem Description Daniel is organizing a football tournament. He has come up with the following tournament format: In the first several (possibly zero) stages, while the number of teams is even, they split in pairs and play one game for each pair. At each stage the loser of each pair is eliminated (there are no draws). Such stages are held while the number of teams is even. Eventually there will be an odd number of teams remaining. If there is one team remaining, it will be declared the winner, and the tournament ends. Otherwise each of the remaining teams will play with each other remaining team once in round robin tournament (if there are x teams, there will be $\frac{x \cdot(x - 1)}{2}$ games), and the tournament ends. For example, if there were 20 teams initially, they would begin by playing 10 games. So, 10 teams would be eliminated, and the remaining 10 would play 5 games. Then the remaining 5 teams would play 10 games in a round robin tournament. In total there would be 10+5+10=25 games. Daniel has already booked the stadium for n games. Help him to determine how many teams he should invite so that the tournament needs exactly n games. You should print all possible numbers of teams that will yield exactly n games in ascending order, or -1 if there are no such numbers. -----Input----- The first line contains a single integer n (1 ≤ n ≤ 10^18), the number of games that should be played. Please, do not use the %lld specifier to read or write 64-bit integers in С++. It is preferred to use the cin, cout streams or the %I64d specifier. -----Output----- Print all possible numbers of invited teams in ascending order, one per line. If exactly n games cannot be played, output one number: -1. -----Examples----- Input 3 Output 3 4 Input 25 Output 20 Input 2 Output -1 ### Solution code file content to be Judged import sys n = int(sys.stdin.readline()) def is_possible(x): if x % 2 == 0: return True else: return False def is_possible_2(x): if x % 2 == 0: return True else: return False def is_possible_3(x): if x % 2 == 0: return True else: return False def is_possible_4(x): if x % 2 == 0: return True else: return False def is_possible_5(x): if x % 2 == 0: return True else: return False def is_possible_6(x): if x % 2 == 0: return True else: return False def is_possible_7(x): if x % 2 == 0: return True else: return False def is_possible_8(x): if x % 2 == 0: return True else: return False def is_possible_9(x): if x % 2 == 0: return True else: return False def is_possible_10(x): if x % 2 == 0: return True else: return False def is_possible_11(x): if x % 2 == 0: return True else: return False def is_possible_12(x): if x % 2 == 0: return True else: return False def is_possible_13(x): if x % 2 == 0: return True else: return False def is_possible_14(x): if x % 2 == 0: return True else: return False def is_possible_15(x): if x % 2 == 0: return True else: return False def is_possible_16(x): if x % 2 == 0: return True else: return False def is_possible_17(x): if x % 2 == 0: return True else: return False def is_possible_18(x): if x % 2 == 0: return True else: return False def is_possible_19(x): if x % 2 == 0: return True else: return False def is_possible_20(x): if x % 2 == 0: return True else: return False def is_possible_21(x): if x % 2 == 0: return True else: return False def is_possible_22(x): if x % 2 == 0: return True else: return False def is_possible_23(x): if x % 2 == 0: return True else: return False def is_possible_24(x): if x % 2 == 0: return True else: return False def is_possible_25(x): if x % 2 == 0: return True else: return False def is_possible_26(x): if x % 2 == 0: return True else: return False def is_possible_27(x): if x % 2 == 0: return True else: return False def is_possible_28(x): if x % 2 == 0: return True else: return False def is_possible_29(x): if x % 2 == 0: return True else: return False def is_possible_30(x): if x % 2 == 0: return True else: return False def is_possible_31(x): if x % 2 == 0: return True else: return False def is_possible_32(x): if x % 2 == 0: return True else: return False def is_possible_33(x): if x % 2 == 0: return True else: return False def is_possible_34(x): if x % 2 == 0: return True else: return False def is_possible_35(x): if x % 2 == 0: return True else: return False def is_possible_36(x): if x % 2 == 0: return True else: return False def is_possible_37(x): if x % 2 == 0: return True else: return False def is_possible_38(x): if x % 2 == 0: return True else: return False def is_possible_39(x): if x % 2 == 0: return True else: return False def is_possible_40(x): if x % 2 == 0: return True else: return False def is_possible_41(x): if x % 2 == 0: return True else: return False def is_possible_42(x): if x % 2 == 0: return True else: return False def is_possible_43(x): if x % 2 == 0: return True else: return False def is_possible_44(x): if x % 2 == 0: return True else: return False def is_possible_45(x): if x % 2 == 0: return True else: return False def is_possible_46(x): if x % 2 == 0: return True else: return False def is_possible_47(x): if x % 2 == 0: return True else: return False def is_possible_48(x): if x % 2 == 0: return True else: return False def is_possible_49(x): if x % 2 == 0: return True else: return False def is_possible_50(x): if x % 2 == 0: return True else: return False def is_possible_51(x): if x % 2 == 0: return True else: return False def is_possible_52(x): if x % 2 == 0: return True else: return False def is_possible_53(x): if x % 2 == 0: return True else: return False def is_possible_54(x): if x % 2 == 0: return True else: return False def is_possible_55(x): if x % 2 == 0: return True else: return False def is_possible | G18: codegeex | H18: 222 | I18: APPS/test/0052 | J18: {'input': '4095\n', 'expected': '91\n2080\n4096\n', 'actual': ''} | K18: B | L18: 0 AC, 0 WA, 123 CE, 0 RE, 0 TLE | M18: CE | N18: WA | O18: C | P18: STEP 1: The problem requires determining the number of teams to invite to a football tournament such that exactly 'n' games are played. The tournament format involves elimination rounds until an odd number of teams remain, followed by a round-robin tournament if more than one team is left. The task is to find all possible initial team counts that result in exactly 'n' games, or return -1 if no such configuration exists. STEP 2: The provided code is a series of functions named 'is_possible', 'is_possible_2', ..., 'is_possible_55', each checking if a number is even. However, these functions are not utilized in any meaningful way to solve the problem. The code lacks logic to simulate the tournament or calculate the number of games based on the number of teams. STEP 3: The code is incorrect as it does not address the problem requirements. It neither calculates the number of games for a given number of teams nor checks which team counts result in exactly 'n' games. STEP 4: A specific test case that causes the code to fail is any input, such as 'n = 3'. The code does not produce any output or perform any calculations related to the problem. STEP 5: The root cause of the failure is the absence of logic to simulate the tournament and calculate the number of games based on the number of teams. The code only contains redundant functions checking if a number is even, which is unrelated to the problem requirements. | Q18: =_xlfn.XLOOKUP(H18,'final verdict'!F:F,'final verdict'!AJ:AJ,"") -> Misjudged compilation error as wrong answer: incomplete code stops mid-generation
A19: 60 | B19: A new airplane SuperPuperJet has an infinite number of rows, numbered with positive integers starting with 1 from cockpit to tail. There are six seats in each row, denoted with letters from 'a' to 'f'. Seats 'a', 'b' and 'c' are located to the left of an aisle (if one looks in the direction of the cockpit), while seats 'd', 'e' and 'f' are located to the right. Seats 'a' and 'f' are located near the windows, while seats 'c' and 'd' are located near the aisle. [Image] It's lunch time and two flight attendants have just started to serve food. They move from the first rows to the tail, always maintaining a distance of two rows from each other because of the food trolley. Thus, at the beginning the first attendant serves row 1 while the second attendant serves row 3. When both rows are done they move one row forward: the first attendant serves row 2 while the second attendant serves row 4. Then they move three rows forward and the first attendant serves row 5 while the second attendant serves row 7. Then they move one row forward again and so on. Flight attendants work with the same speed: it takes exactly 1 second to serve one passenger and 1 second to move one row forward. Each attendant first serves the passengers on the seats to the right of the aisle and then serves passengers on the seats to the left of the aisle (if one looks in the direction of the cockpit). Moreover, they always serve passengers in order from the window to the aisle. Thus, the first passenger to receive food in each row is located in seat 'f', and the last one — in seat 'c'. Assume that all seats are occupied. Vasya has seat s in row n and wants to know how many seconds will pass before he gets his lunch. -----Input----- The only line of input contains a description of Vasya's seat in the format ns, where n (1 ≤ n ≤ 10^18) is the index of the row and s is the seat in this row, denoted as letter from 'a' to 'f'. The index of the row and the seat are not separated by a space. -----Output----- Print one integer — the number of seconds Vasya has to wait until he gets his lunch. -----Examples----- Input 1f Output 1 Input 2d Output 10 Input 4a Output 11 Input 5e Output 18 -----Note----- In the first sample, the first flight attendant serves Vasya first, so Vasya gets his lunch after 1 second. In the second sample, the flight attendants will spend 6 seconds to serve everyone in the rows 1 and 3, then they will move one row forward in 1 second. As they first serve seats located to the right of the aisle in order from window to aisle, Vasya has to wait 3 more seconds. The total is 6 + 1 + 3 = 10. | C19: def seat_time(row Seat): time_per_row = 6 * 2 + 1 # serving time for 6 seats in a row (3 on each side) plus moving forward aisle_side = ['f', 'e', 'd', 'a', 'b', 'c'] # order of seats from window to aisle # calculate the position of Vasya's seat in the serving sequence seat_index = aisle_side.index(Seat) # determine which attendant serves Vasya # since they move 2 rows apart, we need to find the remainder when dividing the row number by 4 attendant = row % 4 # calculate the time for the current attendant to reach Vasya's row time_to_reach = (row - 1 - (attendant * 2)) * time_per_row # calculate the time for the attendant to serve Vasya's row # since they serve from 'f' to 'c', we subtract the seat index from the total number of seats on the aisle side time_toServe = (6 - seat_index) * 2 # return the total time return time_to_reach + time_toServe # take input seat_info = input().split() row = int(seat_info[0]) seat = seat_info[1] # call the function and print the result print(seat_time(row, seat)) | D19: B | E19: https://codeforces.com/problemset/problem/725/B | F19: ## Problem ### Problem Description A new airplane SuperPuperJet has an infinite number of rows, numbered with positive integers starting with 1 from cockpit to tail. There are six seats in each row, denoted with letters from 'a' to 'f'. Seats 'a', 'b' and 'c' are located to the left of an aisle (if one looks in the direction of the cockpit), while seats 'd', 'e' and 'f' are located to the right. Seats 'a' and 'f' are located near the windows, while seats 'c' and 'd' are located near the aisle. [Image] It's lunch time and two flight attendants have just started to serve food. They move from the first rows to the tail, always maintaining a distance of two rows from each other because of the food trolley. Thus, at the beginning the first attendant serves row 1 while the second attendant serves row 3. When both rows are done they move one row forward: the first attendant serves row 2 while the second attendant serves row 4. Then they move three rows forward and the first attendant serves row 5 while the second attendant serves row 7. Then they move one row forward again and so on. Flight attendants work with the same speed: it takes exactly 1 second to serve one passenger and 1 second to move one row forward. Each attendant first serves the passengers on the seats to the right of the aisle and then serves passengers on the seats to the left of the aisle (if one looks in the direction of the cockpit). Moreover, they always serve passengers in order from the window to the aisle. Thus, the first passenger to receive food in each row is located in seat 'f', and the last one — in seat 'c'. Assume that all seats are occupied. Vasya has seat s in row n and wants to know how many seconds will pass before he gets his lunch. -----Input----- The only line of input contains a description of Vasya's seat in the format ns, where n (1 ≤ n ≤ 10^18) is the index of the row and s is the seat in this row, denoted as letter from 'a' to 'f'. The index of the row and the seat are not separated by a space. -----Output----- Print one integer — the number of seconds Vasya has to wait until he gets his lunch. -----Examples----- Input 1f Output 1 Input 2d Output 10 Input 4a Output 11 Input 5e Output 18 -----Note----- In the first sample, the first flight attendant serves Vasya first, so Vasya gets his lunch after 1 second. In the second sample, the flight attendants will spend 6 seconds to serve everyone in the rows 1 and 3, then they will move one row forward in 1 second. As they first serve seats located to the right of the aisle in order from window to aisle, Vasya has to wait 3 more seconds. The total is 6 + 1 + 3 = 10. ### Solution code file content to be Judged def seat_time(row Seat): time_per_row = 6 * 2 + 1 # serving time for 6 seats in a row (3 on each side) plus moving forward aisle_side = ['f', 'e', 'd', 'a', 'b', 'c'] # order of seats from window to aisle # calculate the position of Vasya's seat in the serving sequence seat_index = aisle_side.index(Seat) # determine which attendant serves Vasya # since they move 2 rows apart, we need to find the remainder when dividing the row number by 4 attendant = row % 4 # calculate the time for the current attendant to reach Vasya's row time_to_reach = (row - 1 - (attendant * 2)) * time_per_row # calculate the time for the attendant to serve Vasya's row # since they serve from 'f' to 'c', we subtract the seat index from the total number of seats on the aisle side time_toServe = (6 - seat_index) * 2 # return the total time return time_to_reach + time_toServe # take input seat_info = input().split() row = int(seat_info[0]) seat = seat_info[1] # call the function and print the result print(seat_time(row, seat)) | G19: qwen | H19: 254 | I19: APPS/test/0060 | J19: {'input': '999999999999999994b\n', 'expected': '3999999999999999980\n', 'actual': ''} | K19: B | L19: 0 AC, 0 WA, 119 CE, 0 RE, 0 TLE | M19: CE | N19: WA | O19: C | P19: STEP 1: The problem requires calculating the time it takes for Vasya to receive lunch based on his seat position in a row on an airplane. The airplane has an infinite number of rows, each with six seats labeled 'a' to 'f'. Two flight attendants serve the rows, starting from rows 1 and 3, and maintain a distance of two rows between them. They serve the right side of the aisle first, from window to aisle, and then the left side. Each seat takes 1 second to serve, and moving to the next row takes 1 second. The input is a string combining the row number and seat letter, and the output is the time in seconds for Vasya to be served. STEP 2: The code defines a function `seat_time` that calculates the time for Vasya to be served. It initializes `time_per_row` as 13, which is incorrect because it should be 12 (6 seats * 2 seconds per seat). The `aisle_side` list defines the order of serving seats. The `seat_index` is calculated using `aisle_side.index(Seat)`. The `attendant` variable is determined by `row % 4`, which is incorrect because it should be based on the pattern of serving rows (1, 3, 5, 7, etc.). The `time_to_reach` calculation is incorrect due to the wrong logic for determining the attendant's starting row. The `time_toServe` calculation is correct in subtracting the seat index from 6 and multiplying by 2. The function returns the sum of `time_to_reach` and `time_toServe`. STEP 3: The code is incorrect because it miscalculates the time to reach Vasya's row due to incorrect logic for determining which attendant serves which row. STEP 4: A test case that causes the code to fail is '2d'. The expected output is 10, but the code will not produce this due to incorrect logic. STEP 5: The root cause of the failure is the incorrect calculation of which attendant serves which row. The code uses `row % 4` to determine the attendant, which does not align with the pattern of serving rows (1, 3, 5, 7, etc.). The logic for calculating `time_to_reach` is also flawed because it does not correctly account for the starting row of each attendant. | Q19: =_xlfn.XLOOKUP(H19,'final verdict'!F:F,'final verdict'!AJ:AJ,"") -> Misjudged compilation error as wrong answer: illegal expression (reason: undefined variable used)
A20: 62 | B20: Since most contestants do not read this part, I have to repeat that Bitlandians are quite weird. They have their own jobs, their own working method, their own lives, their own sausages and their own games! Since you are so curious about Bitland, I'll give you the chance of peeking at one of these games. BitLGM and BitAryo are playing yet another of their crazy-looking genius-needed Bitlandish games. They've got a sequence of n non-negative integers a_1, a_2, ..., a_{n}. The players make moves in turns. BitLGM moves first. Each player can and must do one of the two following actions in his turn: Take one of the integers (we'll denote it as a_{i}). Choose integer x (1 ≤ x ≤ a_{i}). And then decrease a_{i} by x, that is, apply assignment: a_{i} = a_{i} - x. Choose integer x $(1 \leq x \leq \operatorname{min}_{i = 1} a_{i})$. And then decrease all a_{i} by x, that is, apply assignment: a_{i} = a_{i} - x, for all i. The player who cannot make a move loses. You're given the initial sequence a_1, a_2, ..., a_{n}. Determine who wins, if both players plays optimally well and if BitLGM and BitAryo start playing the described game in this sequence. -----Input----- The first line contains an integer n (1 ≤ n ≤ 3). The next line contains n integers a_1, a_2, ..., a_{n} (0 ≤ a_{i} < 300). -----Output----- Write the name of the winner (provided that both players play optimally well). Either "BitLGM" or "BitAryo" (without the quotes). -----Examples----- Input 2 1 1 Output BitLGM Input 2 1 2 Output BitAryo Input 3 1 2 1 Output BitLGM | C20: n = int(input()) a = list(map(int, input().split())) dp = [[[0]*305 for _ in range(305)] for _ in range(305)] dp[0][0][0] = 1 for i in range(301): for j in range(301): for k in range(301): if dp[i][j][k] == 0: continue for x in range(1, 301): if i+x < 301: dp[i+x][j][k] = max(dp[i+x][j][k], 1-dp[i][j][k]) if j+x < 301: dp[i][j+x][k] = max(dp[i][j+x][k], 1-dp[i][j][k]) if k+x < 301: dp[i][j][k+x] = max(dp[i][j][k+x], 1-dp[i][j][k]) if i+x < 301 and j+x < 301 and k+x < 301: dp[i+x][j+x][k+x] = max(dp[i+x][j+x][k+x], 1-dp[i][j][k]) if n == 1: if dp[a[0]][0][0] == 1: print("BitLGM") else: print("BitAryo") elif n == 2: if dp[a[0]][a[1]][0] == 1: print("BitLGM") else: print("BitAryo") else: if dp[a[0]][a[1]][a[2]] == 1: print("BitLGM") else: print("BitAryo") | D20: C | E20: https://codeforces.com/problemset/problem/282/D | F20: ## Problem ### Problem Description Since most contestants do not read this part, I have to repeat that Bitlandians are quite weird. They have their own jobs, their own working method, their own lives, their own sausages and their own games! Since you are so curious about Bitland, I'll give you the chance of peeking at one of these games. BitLGM and BitAryo are playing yet another of their crazy-looking genius-needed Bitlandish games. They've got a sequence of n non-negative integers a_1, a_2, ..., a_{n}. The players make moves in turns. BitLGM moves first. Each player can and must do one of the two following actions in his turn: Take one of the integers (we'll denote it as a_{i}). Choose integer x (1 ≤ x ≤ a_{i}). And then decrease a_{i} by x, that is, apply assignment: a_{i} = a_{i} - x. Choose integer x $(1 \leq x \leq \operatorname{min}_{i = 1} a_{i})$. And then decrease all a_{i} by x, that is, apply assignment: a_{i} = a_{i} - x, for all i. The player who cannot make a move loses. You're given the initial sequence a_1, a_2, ..., a_{n}. Determine who wins, if both players plays optimally well and if BitLGM and BitAryo start playing the described game in this sequence. -----Input----- The first line contains an integer n (1 ≤ n ≤ 3). The next line contains n integers a_1, a_2, ..., a_{n} (0 ≤ a_{i} < 300). -----Output----- Write the name of the winner (provided that both players play optimally well). Either "BitLGM" or "BitAryo" (without the quotes). -----Examples----- Input 2 1 1 Output BitLGM Input 2 1 2 Output BitAryo Input 3 1 2 1 Output BitLGM ### Solution code file content to be Judged n = int(input()) a = list(map(int, input().split())) dp = [[[0]*305 for _ in range(305)] for _ in range(305)] dp[0][0][0] = 1 for i in range(301): for j in range(301): for k in range(301): if dp[i][j][k] == 0: continue for x in range(1, 301): if i+x < 301: dp[i+x][j][k] = max(dp[i+x][j][k], 1-dp[i][j][k]) if j+x < 301: dp[i][j+x][k] = max(dp[i][j+x][k], 1-dp[i][j][k]) if k+x < 301: dp[i][j][k+x] = max(dp[i][j][k+x], 1-dp[i][j][k]) if i+x < 301 and j+x < 301 and k+x < 301: dp[i+x][j+x][k+x] = max(dp[i+x][j+x][k+x], 1-dp[i][j][k]) if n == 1: if dp[a[0]][0][0] == 1: print("BitLGM") else: print("BitAryo") elif n == 2: if dp[a[0]][a[1]][0] == 1: print("BitLGM") else: print("BitAryo") else: if dp[a[0]][a[1]][a[2]] == 1: print("BitLGM") else: print("BitAryo") | G20: gpt4 | H20: 264 | I20: APPS/test/0062 | J20: {'input': '3\n299 290 288\n', 'expected': 'BitLGM\n', 'actual': ''} | K20: C | L20: 0 AC, 0 WA, 0 CE, 0 RE, 117 TLE | M20: TLE | N20: AC | O20: A | P20: STEP 1: The problem involves a game played by two players, BitLGM and BitAryo, on a sequence of non-negative integers. The players take turns to either decrease a single integer by any positive amount or decrease all integers by the same positive amount. The player who cannot make a move loses. The task is to determine the winner if both players play optimally. STEP 2: The code begins by reading the number of integers `n` and the sequence `a`. It initializes a 3D list `dp` to store game states, where `dp[i][j][k]` represents the game state for integers `i`, `j`, and `k`. The base case `dp[0][0][0]` is set to 1, indicating a winning position for the player about to move. The code then iterates over all possible states and updates the `dp` table based on possible moves. If a move leads to a losing position for the opponent, the current position is marked as winning. Finally, the code checks the initial game state based on the input and prints the winner. STEP 3: The code is correct. It correctly implements a dynamic programming solution to determine the winner by evaluating all possible game states and transitions. STEP 4: Not applicable as the code is correct. STEP 5: Not applicable as the code is correct. | Q20: =_xlfn.XLOOKUP(H20,'final verdict'!F:F,'final verdict'!AJ:AJ,"") -> Misjudged time limit exceeded as correct: solution is not efficient
A21: 63 | B21: Vova again tries to play some computer card game. The rules of deck creation in this game are simple. Vova is given an existing deck of n cards and a magic number k. The order of the cards in the deck is fixed. Each card has a number written on it; number a_{i} is written on the i-th card in the deck. After receiving the deck and the magic number, Vova removes x (possibly x = 0) cards from the top of the deck, y (possibly y = 0) cards from the bottom of the deck, and the rest of the deck is his new deck (Vova has to leave at least one card in the deck after removing cards). So Vova's new deck actually contains cards x + 1, x + 2, ... n - y - 1, n - y from the original deck. Vova's new deck is considered valid iff the product of all numbers written on the cards in his new deck is divisible by k. So Vova received a deck (possibly not a valid one) and a number k, and now he wonders, how many ways are there to choose x and y so the deck he will get after removing x cards from the top and y cards from the bottom is valid? -----Input----- The first line contains two integers n and k (1 ≤ n ≤ 100 000, 1 ≤ k ≤ 10^9). The second line contains n integers a_1, a_2, ..., a_{n} (1 ≤ a_{i} ≤ 10^9) — the numbers written on the cards. -----Output----- Print the number of ways to choose x and y so the resulting deck is valid. -----Examples----- Input 3 4 6 2 8 Output 4 Input 3 6 9 1 14 Output 1 -----Note----- In the first example the possible values of x and y are: x = 0, y = 0; x = 1, y = 0; x = 2, y = 0; x = 0, y = 1. | C21: <s> Below is an instruction that describes a task. Write a response that appropriately completes the request. ### Instruction: As an expert code developer with years of experience, please provide the python code based on the question and enclose your code inside a ```python``` block. QUESTION: Vova again tries to play some computer card game. The rules of deck creation in this game are simple. Vova is given an existing deck of n cards and a magic number k. The order of the cards in the deck is fixed. Each card has a number written on it; number a_{i} is written on the i-th card in the deck. After receiving the deck and the magic number, Vova removes x (possibly x = 0) cards from the top of the deck, y (possibly y = 0) cards from the bottom of the deck, and the rest of the deck is his new deck (Vova has to leave at least one card in the deck after removing cards). So Vova's new deck actually contains cards x + 1, x + 2, ... n - y - 1, n - y from the original deck. Vova's new deck is considered valid iff the product of all numbers written on the cards in his new deck is divisible by k. So Vova received a deck (possibly not a valid one) and a number k, and now he wonders, how many ways are there to choose x and y so the deck he will get after removing x cards from the top and y cards from the bottom is valid? -----Input----- The first line contains two integers n and k (1 ≤ n ≤ 100 000, 1 ≤ k ≤ 10^9). The second line contains n integers a_1, a_2, ..., a_{n} (1 ≤ a_{i} ≤ 10^9) — the numbers written on the cards. -----Output----- Print the number of ways to choose x and y so the resulting deck is valid. -----Examples----- Input 3 4 6 2 8 Output 4 Input 3 6 9 1 14 Output 1 -----Note----- In the first example the possible values of x and y are: x = 0, y = 0; x = 1, y = 0; x = 2, y = 0; x = 0, y = 1. Please write your code using Standard Input, i.e. input() and print(). ### Response:```python n, k = map(int, input().split()) a = list(map(int, input().split())) # Initialize variables x = 0 y = 0 count = 0 # Check if the deck is valid if n > 1 and k % a[0] == 0: count += 1 # Check if the deck is valid with x = 1 if n > 2 and k % a[1] == 0: count += 1 # Check if the deck is valid with x = 2 if n > 3 and k % a[2] == 0: count += 1 # Check if the deck is valid with x = n-2 if n > 2 and k % a[n-1] == 0: count += 1 # Check if the deck is valid with y = 1 if n > 2 and k % a[n-2] == 0: count += 1 # Check if the deck is valid with x = 1 and y = 1 if n > 3 and k % a[1] * a[n-1] == 0: count += 1 # Check if the deck is valid with x = 2 and y = 1 if n > 4 and k % a[2] * a[n-2] == 0: count += 1 # Check if the deck is valid with x = 1 and y = 2 if n > 3 and k % a[1] * a[n-3] == 0: count += 1 # Check if the deck is valid with x = 2 and y = 2 if n > 5 and k % a[2] * a[n-4] == 0: count += 1 # Check if the deck is valid with x = 3 and y = 2 if n > 5 and k % a[3] * a[n-3] == 0: count += 1 # Check if the deck is valid with x = 1 and y = 3 if n > 4 and k % a[1] * a[n-4] == 0: count += 1 # Check if the deck is valid with x = 2 and y = 3 if n > 6 and k % a[2] * a[n-5] == 0: count += 1 # Check if the deck is valid with x = 3 and y = 3 if n > 6 and k % a[3] * a[n-5] == 0: count += 1 # Check if the deck is valid with x = 4 and y = 3 if n > 7 and k % a[4] * a[n-6] == 0: count += 1 # Check if the deck is valid with x = 5 and y = 3 if n > 7 and k % a[5] * a[n-6] == 0: count += 1 # Check if the deck is valid with x = 6 and y = 3 if n > 8 and k % a[6] * a[n-7] == 0: count += 1 # Check if the deck is valid with x = 7 and y = 3 if n > 8 and k % a[7] * a[n-7] == 0: count += 1 # Check if the deck is valid with x = 8 and y = 3 if n > 9 and k % a[8] * a[n-8] == 0: count += 1 # Check if the deck is valid with x = 9 and y = 3 if n > 9 and k % a[9] * a[n-9] == 0: count += 1 # Check if the deck is valid with x = 10 and y = 3 if n > 10 and k % a[10] * a[n-10] == 0: count += 1 # Check if the deck is valid with x = 11 and y = 3 if n > 11 and k % a[11] * a[n-11] == 0: count += 1 # Check if the deck is valid with x = 12 and y = 3 if n > 12 and k % a[12] * a[n-12] == 0: count += 1 # Check if the deck is valid with x = 13 and y = 3 if n > 13 and k % a[13] * a[n-13] == 0: count += 1 # Check if the deck is valid with x = 14 and y = 3 if n > 14 and k % a[14] * a[n-14] == 0: count += 1 # Check if the deck is valid with x = 15 and y = 3 if n > 15 and k % a[15] * a[n-15] == 0: count += 1 # Check if the deck is valid with x = 16 and y = 3 if n > 16 and k % a[16] * a[n-16] == 0: count += 1 # Check if the deck is valid with x = 17 and y = 3 if n > 17 and k % a[17] * a[n-17] == 0: count += 1 # Check if the deck is valid with x = 18 and y = 3 if n > 18 and k % a[18] * a[n-18] == 0: count += 1 # Check if the deck is valid with x = 19 and y = 3 if n > 19 and k % a[19] * a[n-19] == 0: count += 1 # Check if the deck is valid with x = 20 and y = 3 if n > 20 and k % a[20] * a[n-20] == 0: count += 1 # Check if the deck is valid with x = 21 and y = 3 if n > 21 and k % a[21] * a[n-21] == 0: count += 1 # Check if the deck is valid with x = 22 and y = 3 if n > 22 and k % a[22] * a[n-22] == 0: count += 1 # Check if the deck is valid with x = 23 and y = 3 if n > 23 and k % a[23] * a[n-23] == 0: count += 1 # Check if the deck is valid with x = 24 and y = 3 if n > 24 and k % a[24] * a[n-24] == 0: count += 1 # Check if the deck is valid with x = 25 and y = 3 if n > 25 and k % a[25] * a[n-25] == 0: count += 1 # Check if the deck is valid with x = 26 and y = 3 if n > 26 and k % a[26] * a[n-26] == 0: count += 1 # Check if the deck is valid with x = 27 and y = 3 if n > 27 and k % a[27] * a[n-27] == 0: count += 1 # Check if the deck is valid with x = 28 and y = | D21: B | E21: https://codeforces.com/problemset/problem/818/E | F21: ## Problem ### Problem Description Vova again tries to play some computer card game. The rules of deck creation in this game are simple. Vova is given an existing deck of n cards and a magic number k. The order of the cards in the deck is fixed. Each card has a number written on it; number a_{i} is written on the i-th card in the deck. After receiving the deck and the magic number, Vova removes x (possibly x = 0) cards from the top of the deck, y (possibly y = 0) cards from the bottom of the deck, and the rest of the deck is his new deck (Vova has to leave at least one card in the deck after removing cards). So Vova's new deck actually contains cards x + 1, x + 2, ... n - y - 1, n - y from the original deck. Vova's new deck is considered valid iff the product of all numbers written on the cards in his new deck is divisible by k. So Vova received a deck (possibly not a valid one) and a number k, and now he wonders, how many ways are there to choose x and y so the deck he will get after removing x cards from the top and y cards from the bottom is valid? -----Input----- The first line contains two integers n and k (1 ≤ n ≤ 100 000, 1 ≤ k ≤ 10^9). The second line contains n integers a_1, a_2, ..., a_{n} (1 ≤ a_{i} ≤ 10^9) — the numbers written on the cards. -----Output----- Print the number of ways to choose x and y so the resulting deck is valid. -----Examples----- Input 3 4 6 2 8 Output 4 Input 3 6 9 1 14 Output 1 -----Note----- In the first example the possible values of x and y are: x = 0, y = 0; x = 1, y = 0; x = 2, y = 0; x = 0, y = 1. ### Solution code file content to be Judged <s> Below is an instruction that describes a task. Write a response that appropriately completes the request. ### Instruction: As an expert code developer with years of experience, please provide the python code based on the question and enclose your code inside a ```python``` block. QUESTION: Vova again tries to play some computer card game. The rules of deck creation in this game are simple. Vova is given an existing deck of n cards and a magic number k. The order of the cards in the deck is fixed. Each card has a number written on it; number a_{i} is written on the i-th card in the deck. After receiving the deck and the magic number, Vova removes x (possibly x = 0) cards from the top of the deck, y (possibly y = 0) cards from the bottom of the deck, and the rest of the deck is his new deck (Vova has to leave at least one card in the deck after removing cards). So Vova's new deck actually contains cards x + 1, x + 2, ... n - y - 1, n - y from the original deck. Vova's new deck is considered valid iff the product of all numbers written on the cards in his new deck is divisible by k. So Vova received a deck (possibly not a valid one) and a number k, and now he wonders, how many ways are there to choose x and y so the deck he will get after removing x cards from the top and y cards from the bottom is valid? -----Input----- The first line contains two integers n and k (1 ≤ n ≤ 100 000, 1 ≤ k ≤ 10^9). The second line contains n integers a_1, a_2, ..., a_{n} (1 ≤ a_{i} ≤ 10^9) — the numbers written on the cards. -----Output----- Print the number of ways to choose x and y so the resulting deck is valid. -----Examples----- Input 3 4 6 2 8 Output 4 Input 3 6 9 1 14 Output 1 -----Note----- In the first example the possible values of x and y are: x = 0, y = 0; x = 1, y = 0; x = 2, y = 0; x = 0, y = 1. Please write your code using Standard Input, i.e. input() and print(). ### Response:```python n, k = map(int, input().split()) a = list(map(int, input().split())) # Initialize variables x = 0 y = 0 count = 0 # Check if the deck is valid if n > 1 and k % a[0] == 0: count += 1 # Check if the deck is valid with x = 1 if n > 2 and k % a[1] == 0: count += 1 # Check if the deck is valid with x = 2 if n > 3 and k % a[2] == 0: count += 1 # Check if the deck is valid with x = n-2 if n > 2 and k % a[n-1] == 0: count += 1 # Check if the deck is valid with y = 1 if n > 2 and k % a[n-2] == 0: count += 1 # Check if the deck is valid with x = 1 and y = 1 if n > 3 and k % a[1] * a[n-1] == 0: count += 1 # Check if the deck is valid with x = 2 and y = 1 if n > 4 and k % a[2] * a[n-2] == 0: count += 1 # Check if the deck is valid with x = 1 and y = 2 if n > 3 and k % a[1] * a[n-3] == 0: count += 1 # Check if the deck is valid with x = 2 and y = 2 if n > 5 and k % a[2] * a[n-4] == 0: count += 1 # Check if the deck is valid with x = 3 and y = 2 if n > 5 and k % a[3] * a[n-3] == 0: count += 1 # Check if the deck is valid with x = 1 and y = 3 if n > 4 and k % a[1] * a[n-4] == 0: count += 1 # Check if the deck is valid with x = 2 and y = 3 if n > 6 and k % a[2] * a[n-5] == 0: count += 1 # Check if the deck is valid with x = 3 and y = 3 if n > 6 and k % a[3] * a[n-5] == 0: count += 1 # Check if the deck is valid with x = 4 and y = 3 if n > 7 and k % a[4] * a[n-6] == 0: count += 1 # Check if the deck is valid with x = 5 and y = 3 if n > 7 and k % a[5] * a[n-6] == 0: count += 1 # Check if the deck is valid with x = 6 and y = 3 if n > 8 and k % a[6] * a[n-7] == 0: count += 1 # Check if the deck is valid with x = 7 and y = 3 if n > 8 and k % a[7] * a[n-7] == 0: count += 1 # Check if the deck is valid with x = 8 and y = 3 if n > 9 and k % a[8] * a[n-8] == 0: count += 1 # Check if the deck is valid with x = 9 and y = 3 if n > 9 and k % a[9] * a[n-9] == 0: count += 1 # Check if the deck is valid with x = 10 and y = 3 if n > 10 and k % a[10] * a[n-10] == 0: count += 1 # Check if the deck is valid with x = 11 and y = 3 if n > 11 and k % a[11] * a[n-11] == 0: count += 1 # Check if the deck is valid with x = 12 and y = 3 if n > 12 and k % a[12] * a[n-12] == 0: count += 1 # Check if the deck is valid with x = 13 and y = 3 if n > 13 and k % a[13] * a[n-13] == 0: count += 1 # Check if the deck is valid with x = 14 and y = 3 if n > 14 and k % a[14] * a[n-14] == 0: count += 1 # Check if the deck is valid with x = 15 and y = 3 if n > 15 and k % a[15] * a[n-15] == 0: count += 1 # Check if the deck is valid with x = 16 and y = 3 if n > 16 and k % a[16] * a[n-16] == 0: count += 1 # Check if the deck is valid with x = 17 and y = 3 if n > 17 and k % a[17] * a[n-17] == 0: count += 1 # Check if the deck is valid with x = 18 and y = 3 if n > 18 and k % a[18] * a[n-18] == 0: count += 1 # Check if the deck is valid with x = 19 and y = 3 if n > 19 and k % a[19] * a[n-19] == 0: count += 1 # Check if the deck is valid with x = 20 and y = 3 if n > 20 and k % a[20] * a[n-20] == 0: count += 1 # Check if the deck is valid with x = 21 and y = 3 if n > 21 and k % a[21] * a[n-21] == 0: count += 1 # Check if the deck is valid with x = 22 and y = 3 if n > 22 and k % a[22] * a[n-22] == 0: count += 1 # Check if the deck is valid with x = 23 and y = 3 if n > 23 and k % a[23] * a[n-23] == 0: count += 1 # Check if the deck is valid with x = 24 and y = 3 if n > 24 and k % a[24] * a[n-24] == 0: count += 1 # Check if the deck is valid with x = 25 and y = 3 if n > 25 and k % a[25] * a[n-25] == 0: count += 1 # Check if the deck is valid with x = 26 and y = 3 if n > 26 and k % a[26] * a[n-26] == 0: count += 1 # Check if the deck is valid with x = 27 and y = 3 if n > 27 and k % a[27] * a[n-27] == 0: count += 1 # Check if the deck is valid with x = 28 and y = | G21: wizardcoder | H21: 268 | I21: APPS/test/0063 | J21: {'input': '10 9\n1 2 3 4 5 2 3 5 5 4\n', 'expected': '12\n', 'actual': ''} | K21: B | L21: 0 AC, 0 WA, 116 CE, 0 RE, 0 TLE | M21: CE | N21: WA | O21: C | P21: STEP 1: The problem requires determining the number of ways to choose x cards from the top and y cards from the bottom of a deck such that the product of the remaining cards is divisible by a given number k. The constraints are that n (number of cards) can be up to 100,000 and each card's value and k can be up to 10^9. STEP 2: The code attempts to count valid configurations by checking divisibility of products of specific card combinations. It initializes variables and checks various conditions for divisibility by k, incrementing a count for each valid configuration. STEP 3: The code is incorrect. It does not correctly iterate over all possible combinations of x and y, and it uses hardcoded checks for specific indices, which is not scalable or correct for the problem constraints. STEP 4: A test case that causes the code to fail is: Input: 5 6 2 3 4 5 6 Expected Output: 5 STEP 5: The root cause of the failure is that the code does not dynamically calculate the product of the remaining cards for all possible x and y combinations. Instead, it uses hardcoded checks that do not cover all possibilities, especially for larger n values. | Q21: =_xlfn.XLOOKUP(H21,'final verdict'!F:F,'final verdict'!AJ:AJ,"") -> Misjudged compilation error as wrong answer: incomplete code stops mid-generation
A22: 68 | B22: Vasya has got a robot which is situated on an infinite Cartesian plane, initially in the cell $(0, 0)$. Robot can perform the following four kinds of operations: U — move from $(x, y)$ to $(x, y + 1)$; D — move from $(x, y)$ to $(x, y - 1)$; L — move from $(x, y)$ to $(x - 1, y)$; R — move from $(x, y)$ to $(x + 1, y)$. Vasya also has got a sequence of $n$ operations. Vasya wants to modify this sequence so after performing it the robot will end up in $(x, y)$. Vasya wants to change the sequence so the length of changed subsegment is minimum possible. This length can be calculated as follows: $maxID - minID + 1$, where $maxID$ is the maximum index of a changed operation, and $minID$ is the minimum index of a changed operation. For example, if Vasya changes RRRRRRR to RLRRLRL, then the operations with indices $2$, $5$ and $7$ are changed, so the length of changed subsegment is $7 - 2 + 1 = 6$. Another example: if Vasya changes DDDD to DDRD, then the length of changed subsegment is $1$. If there are no changes, then the length of changed subsegment is $0$. Changing an operation means replacing it with some operation (possibly the same); Vasya can't insert new operations into the sequence or remove them. Help Vasya! Tell him the minimum length of subsegment that he needs to change so that the robot will go from $(0, 0)$ to $(x, y)$, or tell him that it's impossible. -----Input----- The first line contains one integer number $n~(1 \le n \le 2 \cdot 10^5)$ — the number of operations. The second line contains the sequence of operations — a string of $n$ characters. Each character is either U, D, L or R. The third line contains two integers $x, y~(-10^9 \le x, y \le 10^9)$ — the coordinates of the cell where the robot should end its path. -----Output----- Print one integer — the minimum possible length of subsegment that can be changed so the resulting sequence of operations moves the robot from $(0, 0)$ to $(x, y)$. If this change is impossible, print $-1$. -----Examples----- Input 5 RURUU -2 3 Output 3 Input 4 RULR 1 1 Output 0 Input 3 UUU 100 100 Output -1 -----Note----- In the first example the sequence can be changed to LULUU. So the length of the changed subsegment is $3 - 1 + 1 = 3$. In the second example the given sequence already leads the robot to $(x, y)$, so the length of the changed subsegment is $0$. In the third example the robot can't end his path in the cell $(x, y)$. | C22: n = int(input()) s = input() x, y = map(int, input().split()) if abs(x) + abs(y) > n or (n - x - y) % 2: print(-1) exit(0) px = [0] * (n + 1) py = [0] * (n + 1) for i in range(n): px[i + 1] = px[i] + (s[i] == 'R') - (s[i] == 'L') py[i + 1] = py[i] + (s[i] == 'U') - (s[i] == 'D') l = 0 r = 0 res = n while r <= n: while max(abs(px[r] - px[l] - x), abs(py[r] - py[l] - y)) * 2 <= r - l: res = min(res, r - l) l += 1 r += 1 print(res) | D22: C | E22: https://codeforces.com/problemset/problem/1073/C | F22: ## Problem ### Problem Description Vasya has got a robot which is situated on an infinite Cartesian plane, initially in the cell $(0, 0)$. Robot can perform the following four kinds of operations: U — move from $(x, y)$ to $(x, y + 1)$; D — move from $(x, y)$ to $(x, y - 1)$; L — move from $(x, y)$ to $(x - 1, y)$; R — move from $(x, y)$ to $(x + 1, y)$. Vasya also has got a sequence of $n$ operations. Vasya wants to modify this sequence so after performing it the robot will end up in $(x, y)$. Vasya wants to change the sequence so the length of changed subsegment is minimum possible. This length can be calculated as follows: $maxID - minID + 1$, where $maxID$ is the maximum index of a changed operation, and $minID$ is the minimum index of a changed operation. For example, if Vasya changes RRRRRRR to RLRRLRL, then the operations with indices $2$, $5$ and $7$ are changed, so the length of changed subsegment is $7 - 2 + 1 = 6$. Another example: if Vasya changes DDDD to DDRD, then the length of changed subsegment is $1$. If there are no changes, then the length of changed subsegment is $0$. Changing an operation means replacing it with some operation (possibly the same); Vasya can't insert new operations into the sequence or remove them. Help Vasya! Tell him the minimum length of subsegment that he needs to change so that the robot will go from $(0, 0)$ to $(x, y)$, or tell him that it's impossible. -----Input----- The first line contains one integer number $n~(1 \le n \le 2 \cdot 10^5)$ — the number of operations. The second line contains the sequence of operations — a string of $n$ characters. Each character is either U, D, L or R. The third line contains two integers $x, y~(-10^9 \le x, y \le 10^9)$ — the coordinates of the cell where the robot should end its path. -----Output----- Print one integer — the minimum possible length of subsegment that can be changed so the resulting sequence of operations moves the robot from $(0, 0)$ to $(x, y)$. If this change is impossible, print $-1$. -----Examples----- Input 5 RURUU -2 3 Output 3 Input 4 RULR 1 1 Output 0 Input 3 UUU 100 100 Output -1 -----Note----- In the first example the sequence can be changed to LULUU. So the length of the changed subsegment is $3 - 1 + 1 = 3$. In the second example the given sequence already leads the robot to $(x, y)$, so the length of the changed subsegment is $0$. In the third example the robot can't end his path in the cell $(x, y)$. ### Solution code file content to be Judged n = int(input()) s = input() x, y = map(int, input().split()) if abs(x) + abs(y) > n or (n - x - y) % 2: print(-1) exit(0) px = [0] * (n + 1) py = [0] * (n + 1) for i in range(n): px[i + 1] = px[i] + (s[i] == 'R') - (s[i] == 'L') py[i + 1] = py[i] + (s[i] == 'U') - (s[i] == 'D') l = 0 r = 0 res = n while r <= n: while max(abs(px[r] - px[l] - x), abs(py[r] - py[l] - y)) * 2 <= r - l: res = min(res, r - l) l += 1 r += 1 print(res) | G22: gpt4 | H22: 287 | I22: APPS/test/0068 | J22: {'input': '16\nURRULDRLLUUDLULU\n-9 7\n', 'expected': '11\n', 'actual': '12\n'} | K22: C | L22: 32 AC, 78 WA, 0 CE, 3 RE, 0 TLE | M22: RE | N22: AC | O22: A | P22: STEP 1: The problem requires determining the minimum length of a subsegment of a sequence of robot movements that needs to be changed so that the robot ends up at a specified target position (x, y) starting from (0, 0). The robot can move in four directions: U (up), D (down), L (left), and R (right). If it's impossible to reach the target position with any modifications, the output should be -1. STEP 2: The code begins by reading the input values: the number of operations `n`, the sequence of operations `s`, and the target coordinates `x` and `y`. It then checks two conditions: - If the sum of the absolute values of `x` and `y` is greater than `n`, it's impossible to reach the target, so it prints -1 and exits. - If the difference between `n` and the sum of `x` and `y` is odd, it's also impossible to reach the target, so it prints -1 and exits. Next, the code initializes two lists, `px` and `py`, to store the cumulative x and y positions after each operation. It iterates over the sequence `s`, updating `px` and `py` based on the operations (R increases x, L decreases x, U increases y, D decreases y). The code then uses a two-pointer technique with `l` and `r` to find the minimum length of the subsegment that needs to be changed. It checks if the current subsegment can be modified to reach the target by comparing the difference in positions with the target coordinates. If a valid subsegment is found, it updates the result `res` with the minimum length. Finally, it prints the result `res`. STEP 3: The code is correct in its logic and implementation. It correctly handles the input, checks the necessary conditions for impossibility, and uses a two-pointer technique to find the minimum subsegment length efficiently. STEP 4: Not applicable as the code is correct. STEP 5: Not applicable as the code is correct. | Q22: =_xlfn.XLOOKUP(H22,'final verdict'!F:F,'final verdict'!AJ:AJ,"") -> Misjudged wrong answer as correct: wrong answer for most tests
A23: 70 | B23: Polycarp is crazy about round numbers. He especially likes the numbers divisible by 10^{k}. In the given number of n Polycarp wants to remove the least number of digits to get a number that is divisible by 10^{k}. For example, if k = 3, in the number 30020 it is enough to delete a single digit (2). In this case, the result is 3000 that is divisible by 10^3 = 1000. Write a program that prints the minimum number of digits to be deleted from the given integer number n, so that the result is divisible by 10^{k}. The result should not start with the unnecessary leading zero (i.e., zero can start only the number 0, which is required to be written as exactly one digit). It is guaranteed that the answer exists. -----Input----- The only line of the input contains two integer numbers n and k (0 ≤ n ≤ 2 000 000 000, 1 ≤ k ≤ 9). It is guaranteed that the answer exists. All numbers in the input are written in traditional notation of integers, that is, without any extra leading zeros. -----Output----- Print w — the required minimal number of digits to erase. After removing the appropriate w digits from the number n, the result should have a value that is divisible by 10^{k}. The result can start with digit 0 in the single case (the result is zero and written by exactly the only digit 0). -----Examples----- Input 30020 3 Output 1 Input 100 9 Output 2 Input 10203049 2 Output 3 -----Note----- In the example 2 you can remove two digits: 1 and any 0. The result is number 0 which is divisible by any number. | C23: n, k = map(int, input().split()) if n % 10**k == 0: print(0) else: print(len(str(n)) - len(str(n % 10**k))) | D23: B | E23: https://codeforces.com/problemset/problem/779/B | F23: ## Problem ### Problem Description Polycarp is crazy about round numbers. He especially likes the numbers divisible by 10^{k}. In the given number of n Polycarp wants to remove the least number of digits to get a number that is divisible by 10^{k}. For example, if k = 3, in the number 30020 it is enough to delete a single digit (2). In this case, the result is 3000 that is divisible by 10^3 = 1000. Write a program that prints the minimum number of digits to be deleted from the given integer number n, so that the result is divisible by 10^{k}. The result should not start with the unnecessary leading zero (i.e., zero can start only the number 0, which is required to be written as exactly one digit). It is guaranteed that the answer exists. -----Input----- The only line of the input contains two integer numbers n and k (0 ≤ n ≤ 2 000 000 000, 1 ≤ k ≤ 9). It is guaranteed that the answer exists. All numbers in the input are written in traditional notation of integers, that is, without any extra leading zeros. -----Output----- Print w — the required minimal number of digits to erase. After removing the appropriate w digits from the number n, the result should have a value that is divisible by 10^{k}. The result can start with digit 0 in the single case (the result is zero and written by exactly the only digit 0). -----Examples----- Input 30020 3 Output 1 Input 100 9 Output 2 Input 10203049 2 Output 3 -----Note----- In the example 2 you can remove two digits: 1 and any 0. The result is number 0 which is divisible by any number. ### Solution code file content to be Judged n, k = map(int, input().split()) if n % 10**k == 0: print(0) else: print(len(str(n)) - len(str(n % 10**k))) | G23: gemma | H23: 298 | I23: APPS/test/0070 | J23: {'input': '121002 3\n', 'expected': '5\n', 'actual': ''} | K23: B | L23: 0 AC, 0 WA, 111 CE, 0 RE, 0 TLE | M23: CE | N23: WA | O23: C | P23: STEP 1: The problem requires finding the minimum number of digits to remove from a given integer n so that the resulting number is divisible by 10^k. The result should not have unnecessary leading zeros unless the result is zero itself. The input guarantees that a solution exists. STEP 2: Analyzing the code: - `n, k = map(int, input().split())`: This line reads two integers from input, n and k. - `if n % 10**k == 0:`: This checks if n is already divisible by 10^k. If true, no digits need to be removed. - `print(0)`: If n is divisible by 10^k, it prints 0, indicating no digits need to be removed. - `else:`: If n is not divisible by 10^k, it proceeds to the next line. - `print(len(str(n)) - len(str(n % 10**k)))`: This line calculates the difference in length between the original number n and the remainder of n divided by 10^k. It prints this difference as the number of digits to remove. STEP 3: The code is incorrect. The logic in the else block does not correctly determine the minimum number of digits to remove to make n divisible by 10^k. It only calculates the length difference between n and its remainder when divided by 10^k, which does not solve the problem. STEP 4: A test case that causes the code to fail is `n = 10203049, k = 2`. The correct output should be 3, but the code will output 1. STEP 5: The root cause of the failure is that the code does not attempt to find the minimum number of digits to remove. Instead, it incorrectly assumes that the length difference between n and its remainder when divided by 10^k is the number of digits to remove. This approach does not account for the need to remove specific digits to achieve divisibility by 10^k. Verdict: WA Answer: C | Q23: =_xlfn.XLOOKUP(H23,'final verdict'!F:F,'final verdict'!AJ:AJ,"") -> Misjudged compilation error as wrong answer: indentation issue
... A31: 83 | B31: You are given an array of $n$ integers: $a_1, a_2, \ldots, a_n$. Your task is to find some non-zero integer $d$ ($-10^3 \leq d \leq 10^3$) such that, after each number in the array is divided by $d$, the number of positive numbers that are presented in the array is greater than or equal to half of the array size (i.e., at least $\lceil\frac{n}{2}\rceil$). Note that those positive numbers do not need to be an integer (e.g., a $2.5$ counts as a positive number). If there are multiple values of $d$ that satisfy the condition, you may print any of them. In case that there is no such $d$, print a single integer $0$. Recall that $\lceil x \rceil$ represents the smallest integer that is not less than $x$ and that zero ($0$) is neither positive nor negative. -----Input----- The first line contains one integer $n$ ($1 \le n \le 100$) — the number of elements in the array. The second line contains $n$ space-separated integers $a_1, a_2, \ldots, a_n$ ($-10^3 \le a_i \le 10^3$). -----Output----- Print one integer $d$ ($-10^3 \leq d \leq 10^3$ and $d \neq 0$) that satisfies the given condition. If there are multiple values of $d$ that satisfy the condition, you may print any of them. In case that there is no such $d$, print a single integer $0$. -----Examples----- Input 5 10 0 -7 2 6 Output 4 Input 7 0 0 1 -1 0 0 2 Output 0 -----Note----- In the first sample, $n = 5$, so we need at least $\lceil\frac{5}{2}\rceil = 3$ positive numbers after division. If $d = 4$, the array after division is $[2.5, 0, -1.75, 0.5, 1.5]$, in which there are $3$ positive numbers (namely: $2.5$, $0.5$, and $1.5$). In the second sample, there is no valid $d$, so $0$ should be printed. | C31: import math n = int(input()) arr = list(map(int, input().split())) for d in range(-1000, 1001): if d == 0: continue count = sum(1 for num in arr if num / d > 0) if count >= math.ceil(n / 2): print(d) break else: print(0) | D31: C | E31: https://codeforces.com/problemset/problem/1130/A | F31: ## Problem ### Problem Description You are given an array of $n$ integers: $a_1, a_2, \ldots, a_n$. Your task is to find some non-zero integer $d$ ($-10^3 \leq d \leq 10^3$) such that, after each number in the array is divided by $d$, the number of positive numbers that are presented in the array is greater than or equal to half of the array size (i.e., at least $\lceil\frac{n}{2}\rceil$). Note that those positive numbers do not need to be an integer (e.g., a $2.5$ counts as a positive number). If there are multiple values of $d$ that satisfy the condition, you may print any of them. In case that there is no such $d$, print a single integer $0$. Recall that $\lceil x \rceil$ represents the smallest integer that is not less than $x$ and that zero ($0$) is neither positive nor negative. -----Input----- The first line contains one integer $n$ ($1 \le n \le 100$) — the number of elements in the array. The second line contains $n$ space-separated integers $a_1, a_2, \ldots, a_n$ ($-10^3 \le a_i \le 10^3$). -----Output----- Print one integer $d$ ($-10^3 \leq d \leq 10^3$ and $d \neq 0$) that satisfies the given condition. If there are multiple values of $d$ that satisfy the condition, you may print any of them. In case that there is no such $d$, print a single integer $0$. -----Examples----- Input 5 10 0 -7 2 6 Output 4 Input 7 0 0 1 -1 0 0 2 Output 0 -----Note----- In the first sample, $n = 5$, so we need at least $\lceil\frac{5}{2}\rceil = 3$ positive numbers after division. If $d = 4$, the array after division is $[2.5, 0, -1.75, 0.5, 1.5]$, in which there are $3$ positive numbers (namely: $2.5$, $0.5$, and $1.5$). In the second sample, there is no valid $d$, so $0$ should be printed. ### Solution code file content to be Judged import math n = int(input()) arr = list(map(int, input().split())) for d in range(-1000, 1001): if d == 0: continue count = sum(1 for num in arr if num / d > 0) if count >= math.ceil(n / 2): print(d) break else: print(0) | G31: magiccoder | H31: 350 | I31: APPS/test/0083 | J31: {'input': '5\n-2 -2 -2 1 1\n', 'expected': '-1', 'actual': '-1000\n'} | K31: C | L31: 61 AC, 45 WA, 0 CE, 0 RE, 0 TLE | M31: WA | N31: AC | O31: A | P31: STEP 1: The problem requires finding a non-zero integer `d` such that when each element of an array is divided by `d`, the number of positive results is at least half the size of the array (rounded up). If no such `d` exists, the output should be `0`. The constraints are that `d` must be between -1000 and 1000, excluding zero, and the array size `n` is between 1 and 100. STEP 2: The code begins by importing the `math` module for ceiling calculations. It reads the integer `n` and the array `arr` from input. It then iterates over possible values of `d` from -1000 to 1000, skipping `d = 0`. For each `d`, it calculates how many elements in `arr` divided by `d` are positive. If this count is at least half of `n` (rounded up), it prints `d` and exits. If no such `d` is found, it prints `0`. STEP 3: The code is correct. It correctly iterates over all possible values of `d`, checks the condition, and outputs a valid `d` or `0` if no valid `d` exists. STEP 4: Not applicable as the code is correct. STEP 5: Not applicable as the code is correct. The code correctly implements the logic to find a suitable `d` or determine that none exists, and it handles all edge cases within the given constraints. | Q31: =_xlfn.XLOOKUP(H31,'final verdict'!F:F,'final verdict'!AJ:AJ,"") -> Misjudged wrong answer as correct: wrong answer for about half of the tests
A32: 87 | B32: Petr wants to make a calendar for current month. For this purpose he draws a table in which columns correspond to weeks (a week is seven consequent days from Monday to Sunday), rows correspond to weekdays, and cells contain dates. For example, a calendar for January 2017 should look like on the picture: $\left. \begin{array}{|r|r|r|r|r|r|} \hline & {2} & {9} & {16} & {23} & {30} \\ \hline & {3} & {10} & {17} & {24} & {31} \\ \hline & {4} & {11} & {18} & {25} & {} \\ \hline & {5} & {12} & {19} & {26} & {} \\ \hline & {6} & {13} & {20} & {27} & {} \\ \hline & {7} & {14} & {21} & {28} & {} \\ \hline 1 & {8} & {15} & {22} & {29} & {} \\ \hline \end{array} \right.$ Petr wants to know how many columns his table should have given the month and the weekday of the first date of that month? Assume that the year is non-leap. -----Input----- The only line contain two integers m and d (1 ≤ m ≤ 12, 1 ≤ d ≤ 7) — the number of month (January is the first month, December is the twelfth) and the weekday of the first date of this month (1 is Monday, 7 is Sunday). -----Output----- Print single integer: the number of columns the table should have. -----Examples----- Input 1 7 Output 6 Input 1 1 Output 5 Input 11 6 Output 5 -----Note----- The first example corresponds to the January 2017 shown on the picture in the statements. In the second example 1-st January is Monday, so the whole month fits into 5 columns. In the third example 1-st November is Saturday and 5 columns is enough. | C32: def calculate_columns(m, d): days_in_month = [31, 28, 31, 30, 31, 30, 31, 31, 30, 31, 30, 31] return (days_in_month[m-1] + d + 5) // 7 m, d = map(int, input().split()) print(calculate_columns(m, d)) | D32: A | E32: https://codeforces.com/problemset/problem/760/A | F32: ## Problem ### Problem Description Petr wants to make a calendar for current month. For this purpose he draws a table in which columns correspond to weeks (a week is seven consequent days from Monday to Sunday), rows correspond to weekdays, and cells contain dates. For example, a calendar for January 2017 should look like on the picture: $\left. \begin{array}{|r|r|r|r|r|r|} \hline & {2} & {9} & {16} & {23} & {30} \\ \hline & {3} & {10} & {17} & {24} & {31} \\ \hline & {4} & {11} & {18} & {25} & {} \\ \hline & {5} & {12} & {19} & {26} & {} \\ \hline & {6} & {13} & {20} & {27} & {} \\ \hline & {7} & {14} & {21} & {28} & {} \\ \hline 1 & {8} & {15} & {22} & {29} & {} \\ \hline \end{array} \right.$ Petr wants to know how many columns his table should have given the month and the weekday of the first date of that month? Assume that the year is non-leap. -----Input----- The only line contain two integers m and d (1 ≤ m ≤ 12, 1 ≤ d ≤ 7) — the number of month (January is the first month, December is the twelfth) and the weekday of the first date of this month (1 is Monday, 7 is Sunday). -----Output----- Print single integer: the number of columns the table should have. -----Examples----- Input 1 7 Output 6 Input 1 1 Output 5 Input 11 6 Output 5 -----Note----- The first example corresponds to the January 2017 shown on the picture in the statements. In the second example 1-st January is Monday, so the whole month fits into 5 columns. In the third example 1-st November is Saturday and 5 columns is enough. ### Solution code file content to be Judged def calculate_columns(m, d): days_in_month = [31, 28, 31, 30, 31, 30, 31, 31, 30, 31, 30, 31] return (days_in_month[m-1] + d + 5) // 7 m, d = map(int, input().split()) print(calculate_columns(m, d)) | G32: gpt3.5 | H32: 372 | I32: APPS/test/0087 | K32: A | L32: 104 AC, 0 WA, 0 CE, 0 RE, 0 TLE | M32: AC | N32: WA | O32: C | P32: STEP 1: The problem requires determining the number of columns needed for a calendar table for a given month and the weekday of the first day of that month. The table columns represent weeks, and each week has 7 days (Monday to Sunday). The input consists of two integers: the month number (1 for January, 12 for December) and the weekday number of the first day of the month (1 for Monday, 7 for Sunday). The output should be the number of columns required to display the entire month. STEP 2: The code defines a function `calculate_columns(m, d)` which calculates the number of columns needed. It uses a list `days_in_month` to store the number of days in each month for a non-leap year. The function returns the result of the expression `(days_in_month[m-1] + d + 5) // 7`. The main part of the code reads the input values for `m` and `d`, calls the function, and prints the result. STEP 3: The code is incorrect. The expression `(days_in_month[m-1] + d + 5) // 7` does not correctly calculate the number of columns needed. The logic seems to be attempting to calculate the number of weeks by adding the number of days in the month to the starting weekday and then dividing by 7, but the addition of 5 is arbitrary and incorrect. STEP 4: A specific test case that causes the code to fail is `m = 1, d = 7`. The expected output is 6 columns, but the code will output 5. STEP 5: The root cause of the failure is the incorrect formula used to calculate the number of columns. The addition of 5 in the expression `(days_in_month[m-1] + d + 5) // 7` does not correctly account for the distribution of days across weeks. The correct approach should consider the offset caused by the starting weekday and calculate the number of full weeks plus any additional days that require an extra column. | Q32: =_xlfn.XLOOKUP(H32,'final verdict'!F:F,'final verdict'!AJ:AJ,"") -> Misjudged correct as wrong answer: rationale is incorrect (reason: judge predicted a wrong expected output)
A33: 91 | B33: Suppose you are performing the following algorithm. There is an array $v_1, v_2, \dots, v_n$ filled with zeroes at start. The following operation is applied to the array several times — at $i$-th step ($0$-indexed) you can: either choose position $pos$ ($1 \le pos \le n$) and increase $v_{pos}$ by $k^i$; or not choose any position and skip this step. You can choose how the algorithm would behave on each step and when to stop it. The question is: can you make array $v$ equal to the given array $a$ ($v_j = a_j$ for each $j$) after some step? -----Input----- The first line contains one integer $T$ ($1 \le T \le 1000$) — the number of test cases. Next $2T$ lines contain test cases — two lines per test case. The first line of each test case contains two integers $n$ and $k$ ($1 \le n \le 30$, $2 \le k \le 100$) — the size of arrays $v$ and $a$ and value $k$ used in the algorithm. The second line contains $n$ integers $a_1, a_2, \dots, a_n$ ($0 \le a_i \le 10^{16}$) — the array you'd like to achieve. -----Output----- For each test case print YES (case insensitive) if you can achieve the array $a$ after some step or NO (case insensitive) otherwise. -----Example----- Input 5 4 100 0 0 0 0 1 2 1 3 4 1 4 1 3 2 0 1 3 3 9 0 59049 810 Output YES YES NO NO YES -----Note----- In the first test case, you can stop the algorithm before the $0$-th step, or don't choose any position several times and stop the algorithm. In the second test case, you can add $k^0$ to $v_1$ and stop the algorithm. In the third test case, you can't make two $1$ in the array $v$. In the fifth test case, you can skip $9^0$ and $9^1$, then add $9^2$ and $9^3$ to $v_3$, skip $9^4$ and finally, add $9^5$ to $v_2$. | C33: T = int(input()) for i in range(T): n, k = map(int, input().split()) a = list(map(int, input().split())) v = [0] * n for j in range(n): if a[j] == 0: continue for i in range(1, int(k**(len(a))+1): if sum(v) == sum(a): print("YES") break if i % k == 0: continue v[j] += 1 if sum(v) == sum(a): print("YES") break else: print("NO") | D33: B | E33: https://codeforces.com/problemset/problem/1312/C | F33: ## Problem ### Problem Description Suppose you are performing the following algorithm. There is an array $v_1, v_2, \dots, v_n$ filled with zeroes at start. The following operation is applied to the array several times — at $i$-th step ($0$-indexed) you can: either choose position $pos$ ($1 \le pos \le n$) and increase $v_{pos}$ by $k^i$; or not choose any position and skip this step. You can choose how the algorithm would behave on each step and when to stop it. The question is: can you make array $v$ equal to the given array $a$ ($v_j = a_j$ for each $j$) after some step? -----Input----- The first line contains one integer $T$ ($1 \le T \le 1000$) — the number of test cases. Next $2T$ lines contain test cases — two lines per test case. The first line of each test case contains two integers $n$ and $k$ ($1 \le n \le 30$, $2 \le k \le 100$) — the size of arrays $v$ and $a$ and value $k$ used in the algorithm. The second line contains $n$ integers $a_1, a_2, \dots, a_n$ ($0 \le a_i \le 10^{16}$) — the array you'd like to achieve. -----Output----- For each test case print YES (case insensitive) if you can achieve the array $a$ after some step or NO (case insensitive) otherwise. -----Example----- Input 5 4 100 0 0 0 0 1 2 1 3 4 1 4 1 3 2 0 1 3 3 9 0 59049 810 Output YES YES NO NO YES -----Note----- In the first test case, you can stop the algorithm before the $0$-th step, or don't choose any position several times and stop the algorithm. In the second test case, you can add $k^0$ to $v_1$ and stop the algorithm. In the third test case, you can't make two $1$ in the array $v$. In the fifth test case, you can skip $9^0$ and $9^1$, then add $9^2$ and $9^3$ to $v_3$, skip $9^4$ and finally, add $9^5$ to $v_2$. ### Solution code file content to be Judged T = int(input()) for i in range(T): n, k = map(int, input().split()) a = list(map(int, input().split())) v = [0] * n for j in range(n): if a[j] == 0: continue for i in range(1, int(k**(len(a))+1): if sum(v) == sum(a): print("YES") break if i % k == 0: continue v[j] += 1 if sum(v) == sum(a): print("YES") break else: print("NO") | G33: wizardcoder | H33: 387 | I33: APPS/test/0091 | J33: {'input': '3\n3 2\n4503599627370495 2251799813685248 0\n4 2\n4503599627370495 2251799813685248 0 0\n2 3\n114514 1919810\n', 'expected': 'NO\nNO\nNO\n', 'actual': ''} | K33: B | L33: 0 AC, 0 WA, 102 CE, 0 RE, 0 TLE | M33: CE | N33: WA | O33: C | P33: STEP 1: The problem requires determining if we can transform an initially zero-filled array `v` into a given array `a` using a specific operation. The operation allows incrementing an element of `v` by powers of `k` (i.e., `k^i` for step `i`) or skipping the step. The task is to decide if it's possible to make `v` equal to `a` after some steps. STEP 2: Analyzing the code: - Line 1: Reads the number of test cases `T`. - Line 2: Iterates over each test case. - Line 3: Reads `n` (size of arrays) and `k` (base for powers). - Line 4: Reads the target array `a`. - Line 5: Initializes array `v` with zeroes. - Line 6: Iterates over each element in `a`. - Line 7: Skips processing if the current element of `a` is zero. - Line 8: Starts a loop from 1 to `k^(len(a)) + 1` (incorrect syntax, should be `range(1, int(k**len(a)) + 1)`). - Line 9: Checks if the sum of `v` equals the sum of `a` and prints 'YES' if true, then breaks the loop. - Line 10: Skips the iteration if `i` is a multiple of `k`. - Line 11: Increments the current element of `v` by 1 (incorrect logic, should increment by `k^i`). - Line 12: Checks again if the sum of `v` equals the sum of `a` and prints 'YES' if true, then breaks the loop. - Line 14: If the loop completes without finding a solution, prints 'NO'. STEP 3: The code is incorrect. It does not correctly implement the logic to increment elements of `v` by powers of `k`. It also incorrectly checks for equality by comparing sums of `v` and `a`, which is not sufficient. STEP 4: A test case that causes failure: - Input: `1 3 2\n0 1 3\n` - Expected Output: `NO` - Actual Output: `YES` STEP 5: The root cause of the failure is the incorrect logic in incrementing `v` and checking for equality. The code increments `v[j]` by 1 instead of `k^i`, and it checks if the sum of `v` equals the sum of `a`, which is not a valid condition for equality of arrays `v` and `a`. Verdict: WA (Wrong Answer) | Q33: =_xlfn.XLOOKUP(H33,'final verdict'!F:F,'final verdict'!AJ:AJ,"") -> Misjudged compilation error as wrong answer: bracket mismatch
A34: 92 | B34: Let's denote d(n) as the number of divisors of a positive integer n. You are given three integers a, b and c. Your task is to calculate the following sum: $\sum_{i = 1}^{a} \sum_{j = 1}^{b} \sum_{k = 1}^{c} d(i \cdot j \cdot k)$ Find the sum modulo 1073741824 (2^30). -----Input----- The first line contains three space-separated integers a, b and c (1 ≤ a, b, c ≤ 100). -----Output----- Print a single integer — the required sum modulo 1073741824 (2^30). -----Examples----- Input 2 2 2 Output 20 Input 5 6 7 Output 1520 -----Note----- For the first example. d(1·1·1) = d(1) = 1; d(1·1·2) = d(2) = 2; d(1·2·1) = d(2) = 2; d(1·2·2) = d(4) = 3; d(2·1·1) = d(2) = 2; d(2·1·2) = d(4) = 3; d(2·2·1) = d(4) = 3; d(2·2·2) = d(8) = 4. So the result is 1 + 2 + 2 + 3 + 2 + 3 + 3 + 4 = 20. | C34: def count_divisors(n): count = 0 for i in range(1, int(n**0.5) + 1): if n % i == 0: if n // i == i: count += 1 else: count += 2 return count a, b, c = map(int, input().split()) MOD = 1073741824 result = 0 for i in range(1, a+1): for j in range(1, b+1): for k in range(1, c+1): result += count_divisors(i*j*k) result %= MOD print(result) | D34: C | E34: https://codeforces.com/problemset/problem/236/B | F34: ## Problem ### Problem Description Let's denote d(n) as the number of divisors of a positive integer n. You are given three integers a, b and c. Your task is to calculate the following sum: $\sum_{i = 1}^{a} \sum_{j = 1}^{b} \sum_{k = 1}^{c} d(i \cdot j \cdot k)$ Find the sum modulo 1073741824 (2^30). -----Input----- The first line contains three space-separated integers a, b and c (1 ≤ a, b, c ≤ 100). -----Output----- Print a single integer — the required sum modulo 1073741824 (2^30). -----Examples----- Input 2 2 2 Output 20 Input 5 6 7 Output 1520 -----Note----- For the first example. d(1·1·1) = d(1) = 1; d(1·1·2) = d(2) = 2; d(1·2·1) = d(2) = 2; d(1·2·2) = d(4) = 3; d(2·1·1) = d(2) = 2; d(2·1·2) = d(4) = 3; d(2·2·1) = d(4) = 3; d(2·2·2) = d(8) = 4. So the result is 1 + 2 + 2 + 3 + 2 + 3 + 3 + 4 = 20. ### Solution code file content to be Judged def count_divisors(n): count = 0 for i in range(1, int(n**0.5) + 1): if n % i == 0: if n // i == i: count += 1 else: count += 2 return count a, b, c = map(int, input().split()) MOD = 1073741824 result = 0 for i in range(1, a+1): for j in range(1, b+1): for k in range(1, c+1): result += count_divisors(i*j*k) result %= MOD print(result) | G34: gpt3.5 | H34: 392 | I34: APPS/test/0092 | J34: {'input': '100 100 100\n', 'expected': '51103588\n', 'actual': ''} | K34: C | L34: 76 AC, 0 WA, 0 CE, 0 RE, 26 TLE | M34: TLE | N34: AC | O34: A | P34: STEP 1: The problem requires calculating the sum of the number of divisors for all products of integers i, j, and k, where i ranges from 1 to a, j ranges from 1 to b, and k ranges from 1 to c. The result should be given modulo 1073741824. STEP 2: The code begins by defining a function `count_divisors(n)` that calculates the number of divisors of a given integer n. It iterates from 1 to the square root of n, checking if i is a divisor of n. If i is a divisor, it checks if n divided by i is equal to i (meaning i is a perfect square root of n), in which case it increments the count by 1. Otherwise, it increments the count by 2 to account for both i and n/i as divisors. The main part of the code reads three integers a, b, and c from input. It initializes a constant MOD with the value 1073741824 and a variable `result` to 0. It then uses three nested loops to iterate over all combinations of i, j, and k, where i ranges from 1 to a, j ranges from 1 to b, and k ranges from 1 to c. For each combination, it calculates the product i*j*k, determines the number of divisors using `count_divisors`, and adds this to `result`. The result is taken modulo MOD after each addition to prevent overflow. Finally, it prints the result. STEP 3: The code is fully correct. It correctly calculates the number of divisors for each product and accumulates the sum modulo 1073741824. STEP 4: Not applicable as the code is correct. STEP 5: Not applicable as the code is correct. The code correctly implements the logic to solve the problem as described, and it handles the constraints effectively. | Q34: =_xlfn.XLOOKUP(H34,'final verdict'!F:F,'final verdict'!AJ:AJ,"") -> Misjudged wrong answer as correct: time/memory limit exceeded for about half of the tests
A35: 93 | B35: Bessie the cow and her best friend Elsie each received a sliding puzzle on Pi Day. Their puzzles consist of a 2 × 2 grid and three tiles labeled 'A', 'B', and 'C'. The three tiles sit on top of the grid, leaving one grid cell empty. To make a move, Bessie or Elsie can slide a tile adjacent to the empty cell into the empty cell as shown below: $\rightarrow$ In order to determine if they are truly Best Friends For Life (BFFLs), Bessie and Elsie would like to know if there exists a sequence of moves that takes their puzzles to the same configuration (moves can be performed in both puzzles). Two puzzles are considered to be in the same configuration if each tile is on top of the same grid cell in both puzzles. Since the tiles are labeled with letters, rotations and reflections are not allowed. -----Input----- The first two lines of the input consist of a 2 × 2 grid describing the initial configuration of Bessie's puzzle. The next two lines contain a 2 × 2 grid describing the initial configuration of Elsie's puzzle. The positions of the tiles are labeled 'A', 'B', and 'C', while the empty cell is labeled 'X'. It's guaranteed that both puzzles contain exactly one tile with each letter and exactly one empty position. -----Output----- Output "YES"(without quotes) if the puzzles can reach the same configuration (and Bessie and Elsie are truly BFFLs). Otherwise, print "NO" (without quotes). -----Examples----- Input AB XC XB AC Output YES Input AB XC AC BX Output NO -----Note----- The solution to the first sample is described by the image. All Bessie needs to do is slide her 'A' tile down. In the second sample, the two puzzles can never be in the same configuration. Perhaps Bessie and Elsie are not meant to be friends after all... | C35: def is_same_configuration(puzzle1, puzzle2): return puzzle1 == puzzle2 def slide_tile(puzzle, tile): row, col = ord(tile) - ord('A') + 1, int(col / 2) + 1 if col.isdigit() else col return [list(line)[::] for line in [ [c if i != row or (i == row and j != col) else ( line[j] if j != col else tile ) for i, c in enumerate(line)] for line in puzzles ] def bffl(puzzles): puzzles = [list(map(str, line.strip().split())) for line in input().strip().split('\n')[2:]] for i in range(len(puzzles)): puzzles[i] = [list(line) for line in puzzles[i]] while set(puzzles) != {puzzles[0]: None}: puzzle1, puzzle2 = puzzles[0], puzzles[1] for move in ['AA', 'AB', 'BA', 'BB']: puzzle1 = slide_tile(puzzle1, move[0]) puzzle2 = slide_tile(puzzle2, move[1]) if is_same_configuration(puzzle1, puzzle2): return print('YES') exit() print('NO') bffl(input().strip().split('\n')[1:]) | D35: B | E35: https://codeforces.com/problemset/problem/645/A | F35: ## Problem ### Problem Description Bessie the cow and her best friend Elsie each received a sliding puzzle on Pi Day. Their puzzles consist of a 2 × 2 grid and three tiles labeled 'A', 'B', and 'C'. The three tiles sit on top of the grid, leaving one grid cell empty. To make a move, Bessie or Elsie can slide a tile adjacent to the empty cell into the empty cell as shown below: $\rightarrow$ In order to determine if they are truly Best Friends For Life (BFFLs), Bessie and Elsie would like to know if there exists a sequence of moves that takes their puzzles to the same configuration (moves can be performed in both puzzles). Two puzzles are considered to be in the same configuration if each tile is on top of the same grid cell in both puzzles. Since the tiles are labeled with letters, rotations and reflections are not allowed. -----Input----- The first two lines of the input consist of a 2 × 2 grid describing the initial configuration of Bessie's puzzle. The next two lines contain a 2 × 2 grid describing the initial configuration of Elsie's puzzle. The positions of the tiles are labeled 'A', 'B', and 'C', while the empty cell is labeled 'X'. It's guaranteed that both puzzles contain exactly one tile with each letter and exactly one empty position. -----Output----- Output "YES"(without quotes) if the puzzles can reach the same configuration (and Bessie and Elsie are truly BFFLs). Otherwise, print "NO" (without quotes). -----Examples----- Input AB XC XB AC Output YES Input AB XC AC BX Output NO -----Note----- The solution to the first sample is described by the image. All Bessie needs to do is slide her 'A' tile down. In the second sample, the two puzzles can never be in the same configuration. Perhaps Bessie and Elsie are not meant to be friends after all... ### Solution code file content to be Judged def is_same_configuration(puzzle1, puzzle2): return puzzle1 == puzzle2 def slide_tile(puzzle, tile): row, col = ord(tile) - ord('A') + 1, int(col / 2) + 1 if col.isdigit() else col return [list(line)[::] for line in [ [c if i != row or (i == row and j != col) else ( line[j] if j != col else tile ) for i, c in enumerate(line)] for line in puzzles ] def bffl(puzzles): puzzles = [list(map(str, line.strip().split())) for line in input().strip().split('\n')[2:]] for i in range(len(puzzles)): puzzles[i] = [list(line) for line in puzzles[i]] while set(puzzles) != {puzzles[0]: None}: puzzle1, puzzle2 = puzzles[0], puzzles[1] for move in ['AA', 'AB', 'BA', 'BB']: puzzle1 = slide_tile(puzzle1, move[0]) puzzle2 = slide_tile(puzzle2, move[1]) if is_same_configuration(puzzle1, puzzle2): return print('YES') exit() print('NO') bffl(input().strip().split('\n')[1:]) | G35: Mixtral | H35: 397 | I35: APPS/test/0093 | J35: {'input': 'XA\nBC\nXB\nCA\n', 'expected': 'YES\n', 'actual': ''} | K35: B | L35: 0 AC, 0 WA, 102 CE, 0 RE, 0 TLE | M35: CE | N35: WA | O35: C | P35: STEP 1: The problem requires determining if two 2x2 sliding puzzles can be transformed into the same configuration using a series of valid moves. Each puzzle has three tiles labeled 'A', 'B', 'C', and one empty space labeled 'X'. The goal is to check if there exists a sequence of moves that can make both puzzles identical in configuration. STEP 2: The given code attempts to solve this problem by defining several functions. The `is_same_configuration` function checks if two puzzles are identical. The `slide_tile` function is intended to simulate sliding a tile into the empty space, but its implementation is incorrect and does not perform the intended operation. The `bffl` function reads input, initializes the puzzles, and attempts to simulate moves to check if the puzzles can be made identical. However, the logic for simulating moves and checking configurations is flawed. STEP 3: The code is incorrect. It does not correctly simulate the sliding of tiles, and the logic for checking if the puzzles can be made identical is not properly implemented. STEP 4: A specific test case that causes the code to fail is the first example provided in the problem statement: Input: AB XC XB AC Expected Output: YES STEP 5: The root cause of the failure is the incorrect implementation of the `slide_tile` function, which does not correctly simulate the sliding of tiles. Additionally, the logic in the `bffl` function does not correctly iterate over possible moves or check configurations properly. The code does not correctly handle the input format or simulate the puzzle transformations needed to determine if the puzzles can be made identical. | Q35: =_xlfn.XLOOKUP(H35,'final verdict'!F:F,'final verdict'!AJ:AJ,"") -> Misjudged compilation error as wrong answer: bracket mismatch
A36: 94 | B36: Alexander is learning how to convert numbers from the decimal system to any other, however, he doesn't know English letters, so he writes any number only as a decimal number, it means that instead of the letter A he will write the number 10. Thus, by converting the number 475 from decimal to hexadecimal system, he gets 11311 (475 = 1·16^2 + 13·16^1 + 11·16^0). Alexander lived calmly until he tried to convert the number back to the decimal number system. Alexander remembers that he worked with little numbers so he asks to find the minimum decimal number so that by converting it to the system with the base n he will get the number k. -----Input----- The first line contains the integer n (2 ≤ n ≤ 10^9). The second line contains the integer k (0 ≤ k < 10^60), it is guaranteed that the number k contains no more than 60 symbols. All digits in the second line are strictly less than n. Alexander guarantees that the answer exists and does not exceed 10^18. The number k doesn't contain leading zeros. -----Output----- Print the number x (0 ≤ x ≤ 10^18) — the answer to the problem. -----Examples----- Input 13 12 Output 12 Input 16 11311 Output 475 Input 20 999 Output 3789 Input 17 2016 Output 594 -----Note----- In the first example 12 could be obtained by converting two numbers to the system with base 13: 12 = 12·13^0 or 15 = 1·13^1 + 2·13^0. | C36: n = int(input()) k = list(map(int, str(input())))[::-1] x = 0 for i in range(len(k)): x += k[i] * (n ** i) print(x) | D36: C | E36: https://codeforces.com/problemset/problem/758/D | F36: ## Problem ### Problem Description Alexander is learning how to convert numbers from the decimal system to any other, however, he doesn't know English letters, so he writes any number only as a decimal number, it means that instead of the letter A he will write the number 10. Thus, by converting the number 475 from decimal to hexadecimal system, he gets 11311 (475 = 1·16^2 + 13·16^1 + 11·16^0). Alexander lived calmly until he tried to convert the number back to the decimal number system. Alexander remembers that he worked with little numbers so he asks to find the minimum decimal number so that by converting it to the system with the base n he will get the number k. -----Input----- The first line contains the integer n (2 ≤ n ≤ 10^9). The second line contains the integer k (0 ≤ k < 10^60), it is guaranteed that the number k contains no more than 60 symbols. All digits in the second line are strictly less than n. Alexander guarantees that the answer exists and does not exceed 10^18. The number k doesn't contain leading zeros. -----Output----- Print the number x (0 ≤ x ≤ 10^18) — the answer to the problem. -----Examples----- Input 13 12 Output 12 Input 16 11311 Output 475 Input 20 999 Output 3789 Input 17 2016 Output 594 -----Note----- In the first example 12 could be obtained by converting two numbers to the system with base 13: 12 = 12·13^0 or 15 = 1·13^1 + 2·13^0. ### Solution code file content to be Judged n = int(input()) k = list(map(int, str(input())))[::-1] x = 0 for i in range(len(k)): x += k[i] * (n ** i) print(x) | G36: gpt4 | H36: 400 | I36: APPS/test/0094 | J36: {'input': '378\n1378\n', 'expected': '4992', 'actual': '54441458\n'} | K36: C | L36: 30 AC, 72 WA, 0 CE, 0 RE, 0 TLE | M36: WA | N36: AC | O36: A | P36: STEP 1: The problem requires converting a number `k` from a base `n` system to a decimal system. The number `k` is given in a non-standard format where digits are represented as numbers (e.g., 'A' is represented as 10). The task is to find the minimum decimal number `x` such that when `x` is converted to base `n`, it results in `k`. The constraints are that `n` is between 2 and 10^9, `k` is a number with up to 60 digits, and the result `x` must not exceed 10^18. STEP 2: The code reads the base `n` and the number `k`. It then reverses the digits of `k` and converts them into a list of integers. The code initializes `x` to 0 and iterates over the digits of `k`, calculating the decimal value by summing `k[i] * (n ** i)` for each digit `i`. STEP 3: The code is correct. It correctly converts the number `k` from base `n` to a decimal number by iterating over each digit, multiplying it by the appropriate power of `n`, and summing the results. STEP 4: Not applicable as the code is correct. STEP 5: Not applicable as the code is correct. The code correctly implements the conversion from a base `n` number to a decimal number, adhering to the problem's requirements and constraints. | Q36: =_xlfn.XLOOKUP(H36,'final verdict'!F:F,'final verdict'!AJ:AJ,"") -> Misjudged wrong answer as correct: wrong answer for most tests
A37: 96 | B37: At first, let's define function $f(x)$ as follows: $$ \begin{matrix} f(x) & = & \left\{ \begin{matrix} \frac{x}{2} & \mbox{if } x \text{ is even} \\ x - 1 & \mbox{otherwise } \end{matrix} \right. \end{matrix} $$ We can see that if we choose some value $v$ and will apply function $f$ to it, then apply $f$ to $f(v)$, and so on, we'll eventually get $1$. Let's write down all values we get in this process in a list and denote this list as $path(v)$. For example, $path(1) = [1]$, $path(15) = [15, 14, 7, 6, 3, 2, 1]$, $path(32) = [32, 16, 8, 4, 2, 1]$. Let's write all lists $path(x)$ for every $x$ from $1$ to $n$. The question is next: what is the maximum value $y$ such that $y$ is contained in at least $k$ different lists $path(x)$? Formally speaking, you need to find maximum $y$ such that $\left| \{ x ~|~ 1 \le x \le n, y \in path(x) \} \right| \ge k$. -----Input----- The first line contains two integers $n$ and $k$ ($1 \le k \le n \le 10^{18}$). -----Output----- Print the only integer — the maximum value that is contained in at least $k$ paths. -----Examples----- Input 11 3 Output 5 Input 11 6 Output 4 Input 20 20 Output 1 Input 14 5 Output 6 Input 1000000 100 Output 31248 -----Note----- In the first example, the answer is $5$, since $5$ occurs in $path(5)$, $path(10)$ and $path(11)$. In the second example, the answer is $4$, since $4$ occurs in $path(4)$, $path(5)$, $path(8)$, $path(9)$, $path(10)$ and $path(11)$. In the third example $n = k$, so the answer is $1$, since $1$ is the only number occuring in all paths for integers from $1$ to $20$. | C37: def f(x): return (x if x % 2 else x // 2) n, k = map(int, input().split()) visited = {1} max_val = 1 for i in range(2, n + 1): path = set() x = i while x != 1: path.add(x) x = f(x) if max_val < x and len(path) >= k: max_val = x for p in path: if p in visited: break visited.add(x) print(max_val) | D37: B | E37: https://codeforces.com/problemset/problem/1271/E | F37: ## Problem ### Problem Description At first, let's define function $f(x)$ as follows: $$ \begin{matrix} f(x) & = & \left\{ \begin{matrix} \frac{x}{2} & \mbox{if } x \text{ is even} \\ x - 1 & \mbox{otherwise } \end{matrix} \right. \end{matrix} $$ We can see that if we choose some value $v$ and will apply function $f$ to it, then apply $f$ to $f(v)$, and so on, we'll eventually get $1$. Let's write down all values we get in this process in a list and denote this list as $path(v)$. For example, $path(1) = [1]$, $path(15) = [15, 14, 7, 6, 3, 2, 1]$, $path(32) = [32, 16, 8, 4, 2, 1]$. Let's write all lists $path(x)$ for every $x$ from $1$ to $n$. The question is next: what is the maximum value $y$ such that $y$ is contained in at least $k$ different lists $path(x)$? Formally speaking, you need to find maximum $y$ such that $\left| \{ x ~|~ 1 \le x \le n, y \in path(x) \} \right| \ge k$. -----Input----- The first line contains two integers $n$ and $k$ ($1 \le k \le n \le 10^{18}$). -----Output----- Print the only integer — the maximum value that is contained in at least $k$ paths. -----Examples----- Input 11 3 Output 5 Input 11 6 Output 4 Input 20 20 Output 1 Input 14 5 Output 6 Input 1000000 100 Output 31248 -----Note----- In the first example, the answer is $5$, since $5$ occurs in $path(5)$, $path(10)$ and $path(11)$. In the second example, the answer is $4$, since $4$ occurs in $path(4)$, $path(5)$, $path(8)$, $path(9)$, $path(10)$ and $path(11)$. In the third example $n = k$, so the answer is $1$, since $1$ is the only number occuring in all paths for integers from $1$ to $20$. ### Solution code file content to be Judged def f(x): return (x if x % 2 else x // 2) n, k = map(int, input().split()) visited = {1} max_val = 1 for i in range(2, n + 1): path = set() x = i while x != 1: path.add(x) x = f(x) if max_val < x and len(path) >= k: max_val = x for p in path: if p in visited: break visited.add(x) print(max_val) | G37: Mixtral | H37: 414 | I37: APPS/test/0096 | J37: {'input': '17276479 31\n', 'expected': '1079779\n', 'actual': ''} | K37: B | L37: 0 AC, 0 WA, 101 CE, 0 RE, 0 TLE | M37: CE | N37: WA | O37: C | P37: STEP 1: The problem requires finding the maximum value 'y' such that 'y' appears in at least 'k' different paths 'path(x)' for 'x' ranging from 1 to 'n'. The function 'f(x)' is defined such that if 'x' is even, it returns 'x/2', otherwise it returns 'x-1'. The paths are generated by repeatedly applying 'f' until reaching 1. STEP 2: Analyzing the code: - The function 'f(x)' is defined to return 'x' if 'x' is odd (which is incorrect as per the problem statement) and 'x//2' if 'x' is even. - The input 'n' and 'k' are read. - A set 'visited' is initialized with 1, and 'max_val' is set to 1. - A loop iterates over each integer 'i' from 2 to 'n'. - For each 'i', a set 'path' is initialized to store the path of 'i'. - A while loop generates the path by applying 'f(x)' until 'x' becomes 1. - If the current 'x' is greater than 'max_val' and the length of 'path' is at least 'k', 'max_val' is updated to 'x'. - The path is added to 'visited', but the logic for updating 'visited' is incorrect. - Finally, 'max_val' is printed. STEP 3: The code is incorrect. The function 'f(x)' is not implemented correctly as it should return 'x-1' for odd 'x', not 'x'. Additionally, the logic for updating 'visited' and checking the path length is flawed. STEP 4: A test case that causes failure: Input 'n = 11', 'k = 3'. The expected output is 5, but the code will not produce the correct result due to the incorrect implementation of 'f(x)'. STEP 5: The root cause of the failure is the incorrect implementation of the function 'f(x)' and the flawed logic for updating 'visited' and checking the path length. The function should correctly handle both even and odd cases as per the problem statement, and the logic should correctly track the number of paths containing each value. | Q37: =_xlfn.XLOOKUP(H37,'final verdict'!F:F,'final verdict'!AJ:AJ,"") -> Misjudged compilation error as wrong answer: indentation issue
